{"name": "Super League 1", "nation": "Gr\u00e9cia", "amount_of_clubs": "14times", "amount_of_players": "425", "market_value": "283,53 milh\u00f5es \u20ac", "clubs": [{"name": "AELarisa", "amount_of_players": "27", "media_age": "26,2", "market_value": "6,65 milh\u00f5es \u20ac", "manager": {"name": "Michalis Grigoriou", "nation": "Gr\u00e9cia", "age": "46", "contract_expires": "-", "since": "09/08/2019"}, "players": [{"name": "Gergely Nagy", "position": "Goleiro", "number": "1", "market_value": "200 mil \u20ac", "age": "26", "date_of_birth": "27/05/1994", "nation": "Hungria", "contract_expires": "30/06/2022"}, {"name": "Vladimir Bajic", "position": "Goleiro", "number": "19", "market_value": "200 mil \u20ac", "age": "32", "date_of_birth": "28/11/1987", "nation": "S\u00e9rvia", "contract_expires": "30/06/2022"}, {"name": "Stefanos Souloukos", "position": "Goleiro", "number": "67", "market_value": "50 mil \u20ac", "age": "19", "date_of_birth": "04/01/2001", "nation": "Gr\u00e9cia", "contract_expires": "30/06/2024"}, {"name": "Nikola Zizic", "position": "Zagueiro", "number": "16", "market_value": "250 mil \u20ac", "age": "32", "date_of_birth": "23/01/1988", "nation": "Cro\u00e1cia", "contract_expires": "30/06/2022"}, {"name": "Alexios Michail", "position": "Zagueiro", "number": "5", "market_value": "200 mil \u20ac", "age": "34", "date_of_birth": "18/08/1986", "nation": "Gr\u00e9cia", "contract_expires": "30/06/2021"}, {"name": "Theocharis Iliadis", "position": "Zagueiro", "number": "4", "market_value": "150 mil \u20ac", "age": "24", "date_of_birth": "05/09/1996", "nation": "Gr\u00e9cia", "contract_expires": "30/06/2022"}, {"name": "Charilaos Fourkiotis", "position": "Zagueiro", "number": "3", "market_value": "-\u00a0\u20ac", "age": "19", "date_of_birth": "04/03/2001", "nation": "Gr\u00e9cia", "contract_expires": "30/06/2024"}, {"name": "Mateo Muzek", "position": "Lateral Esq.", "number": "13", "market_value": "450 mil \u20ac", "age": "25", "date_of_birth": "29/04/1995", "nation": "Cro\u00e1cia", "contract_expires": "30/06/2022"}, {"name": "Steliano Filip", "position": "Lateral Esq.", "number": "7", "market_value": "300 mil \u20ac", "age": "26", "date_of_birth": "15/05/1994", "nation": "Rom\u00e9nia", "contract_expires": "30/06/2021"}, {"name": "Georgios Maidanos", "position": "Lateral Esq.", "number": "23", "market_value": "-\u00a0\u20ac", "age": "22", "date_of_birth": "12/04/1998", "nation": "Gr\u00e9cia", "contract_expires": "30/06/2024"}, {"name": "Manolis Bertos", "position": "Lateral Dir.", "number": "25", "market_value": "300 mil \u20ac", "age": "31", "date_of_birth": "13/05/1989", "nation": "Gr\u00e9cia", "contract_expires": "30/06/2022"}, {"name": "Orestis Grigoropoulos", "position": "Lateral Dir.", "number": "24", "market_value": "-\u00a0\u20ac", "age": "20", "date_of_birth": "04/07/2000", "nation": "Gr\u00e9cia", "contract_expires": "30/06/2024"}, {"name": "Aly Ghazal", "position": "Volante", "number": "66", "market_value": "500 mil \u20ac", "age": "28", "date_of_birth": "01/02/1992", "nation": "Egito", "contract_expires": "30/06/2021"}, {"name": "Tim Sparv", "position": "Volante", "number": "6", "market_value": "250 mil \u20ac", "age": "33", "date_of_birth": "20/02/1987", "nation": "Finl\u00e2ndia", "contract_expires": "30/06/2022"}, {"name": "Radomir Milosavljevic", "position": "Meia central", "number": "8", "market_value": "700 mil \u20ac", "age": "28", "date_of_birth": "28/07/1992", "nation": "S\u00e9rvia", "contract_expires": "30/06/2022"}, {"name": "Adnan Secerovic", "position": "Meia central", "number": "22", "market_value": "400 mil \u20ac", "age": "28", "date_of_birth": "01/12/1991", "nation": "B\u00f3snia-Herzegovina", "contract_expires": "30/06/2021"}, {"name": "Dimitrios Pinakas", "position": "Meia Ofensivo", "number": "17", "market_value": "100 mil \u20ac", "age": "19", "date_of_birth": "01/09/2001", "nation": "Gr\u00e9cia", "contract_expires": "30/06/2023"}, {"name": "Alexandros Chalatsis", "position": "Meia Ofensivo", "number": "20", "market_value": "-\u00a0\u20ac", "age": "20", "date_of_birth": "16/06/2000", "nation": "Gr\u00e9cia", "contract_expires": "30/06/2024"}, {"name": "Georgios Zacharakis", "position": "Atacante", "number": "21", "market_value": "-\u00a0\u20ac", "age": "19", "date_of_birth": "02/01/2001", "nation": "Gr\u00e9cia", "contract_expires": "30/06/2024"}, {"name": "Nikola Trujic", "position": "Ponta esquerda", "number": "92", "market_value": "300 mil \u20ac", "age": "28", "date_of_birth": "14/04/1992", "nation": "S\u00e9rvia", "contract_expires": "30/06/2022"}, {"name": "Vin\u00edcius", "position": "Ponta Direita", "number": "77", "market_value": "500 mil \u20ac", "age": "27", "date_of_birth": "03/08/1993", "nation": "Brasil", "contract_expires": "30/06/2021"}, {"name": "Gabriel Torje", "position": "Ponta Direita", "number": "10", "market_value": "450 mil \u20ac", "age": "30", "date_of_birth": "22/11/1989", "nation": "Rom\u00e9nia", "contract_expires": "30/06/2021"}, {"name": "Vangelis Platellas", "position": "Ponta Direita", "number": "11", "market_value": "250 mil \u20ac", "age": "31", "date_of_birth": "01/12/1988", "nation": "Gr\u00e9cia", "contract_expires": "30/06/2022"}, {"name": "Spyros Glynos", "position": "Ponta Direita", "number": "14", "market_value": "150 mil \u20ac", "age": "22", "date_of_birth": "02/12/1997", "nation": "Gr\u00e9cia", "contract_expires": "30/06/2023"}, {"name": "Dimitrios Loufakis", "position": "Ponta Direita", "number": "27", "market_value": "50 mil \u20ac", "age": "20", "date_of_birth": "01/04/2000", "nation": "Gr\u00e9cia", "contract_expires": "30/06/2023"}, {"name": "Fiorin Durmishaj", "position": "Centroavante", "number": "9", "market_value": "500 mil \u20ac", "age": "23", "date_of_birth": "14/11/1996", "nation": "Gr\u00e9cia", "contract_expires": "30/06/2021"}, {"name": "Marko Nunic", "position": "Centroavante", "number": "33", "market_value": "400 mil \u20ac", "age": "27", "date_of_birth": "16/03/1993", "nation": "Eslov\u00e9nia", "contract_expires": "30/06/2021"}]}, {"name": "VolosNPS", "amount_of_players": "27", "media_age": "26,1", "market_value": "6,63 milh\u00f5es \u20ac", "manager": {"name": "\u00c1ngel L\u00f3pez", "nation": "Espanha", "age": "37", "contract_expires": "30/06/2021", "since": "03/09/2020"}, "players": [{"name": "Athanasios Garavelis", "position": "Goleiro", "number": "1", "market_value": "350 mil \u20ac", "age": "28", "date_of_birth": "06/08/1992", "nation": "Gr\u00e9cia", "contract_expires": "30/06/2021"}, {"name": "Boris Klaiman", "position": "Goleiro", "number": "55", "market_value": "300 mil \u20ac", "age": "29", "date_of_birth": "26/10/1990", "nation": "Israel", "contract_expires": "30/06/2022"}, {"name": "Anastasios Karagiozis", "position": "Goleiro", "number": "13", "market_value": "150 mil \u20ac", "age": "23", "date_of_birth": "20/06/1997", "nation": "Gr\u00e9cia", "contract_expires": "30/06/2021"}, {"name": "Symeon Papadopoulos", "position": "Goleiro", "number": "30", "market_value": "100 mil \u20ac", "age": "20", "date_of_birth": "18/04/2000", "nation": "Gr\u00e9cia", "contract_expires": "-"}, {"name": "Vasilios Kravaritis", "position": "Goleiro", "number": "71", "market_value": "50 mil \u20ac", "age": "18", "date_of_birth": "03/04/2002", "nation": "Gr\u00e9cia", "contract_expires": "30/06/2022"}, {"name": "Salvador S\u00e1nchez", "position": "Zagueiro", "number": "5", "market_value": "300 mil \u20ac", "age": "25", "date_of_birth": "31/07/1995", "nation": "Argentina", "contract_expires": "30/06/2022"}, {"name": "Stergios Dimopoulos", "position": "Zagueiro", "number": "33", "market_value": "300 mil \u20ac", "age": "30", "date_of_birth": "25/05/1990", "nation": "Gr\u00e9cia", "contract_expires": "30/06/2022"}, {"name": "Rodrigo Colombo", "position": "Zagueiro", "number": "15", "market_value": "250 mil \u20ac", "age": "27", "date_of_birth": "19/11/1992", "nation": "Argentina", "contract_expires": "-"}, {"name": "Gerasimos Mitoglou", "position": "Zagueiro", "number": "24", "market_value": "100 mil \u20ac", "age": "20", "date_of_birth": "20/10/1999", "nation": "Gr\u00e9cia", "contract_expires": "30/06/2021"}, {"name": "Pavlos Logaras", "position": "Zagueiro", "number": "99", "market_value": "-\u00a0\u20ac", "age": "18", "date_of_birth": "18/06/2002", "nation": "Gr\u00e9cia", "contract_expires": "30/06/2023"}, {"name": "Franco Ferrari", "position": "Lateral Esq.", "number": "3", "market_value": "350 mil \u20ac", "age": "28", "date_of_birth": "09/05/1992", "nation": "Argentina", "contract_expires": "30/06/2021"}, {"name": "Giannis Kiakos", "position": "Lateral Esq.", "number": "31", "market_value": "100 mil \u20ac", "age": "22", "date_of_birth": "14/02/1998", "nation": "Gr\u00e9cia", "contract_expires": "30/06/2021"}, {"name": "Antonis Dentakis", "position": "Lateral Dir.", "number": "2", "market_value": "350 mil \u20ac", "age": "25", "date_of_birth": "13/03/1995", "nation": "Gr\u00e9cia", "contract_expires": "30/06/2021"}, {"name": "Tekio", "position": "Lateral Dir.", "number": "22", "market_value": "325 mil \u20ac", "age": "30", "date_of_birth": "30/07/1990", "nation": "Espanha", "contract_expires": "30/06/2021"}, {"name": "Anastasios Tsokanis", "position": "Volante", "number": "6", "market_value": "350 mil \u20ac", "age": "29", "date_of_birth": "02/05/1991", "nation": "Gr\u00e9cia", "contract_expires": "30/06/2021"}, {"name": "Daan Rienstra", "position": "Meia central", "number": "23", "market_value": "325 mil \u20ac", "age": "27", "date_of_birth": "06/10/1992", "nation": "Holanda", "contract_expires": "30/06/2022"}, {"name": "Simon Lundevall", "position": "Meia Esquerda", "number": "-", "market_value": "225 mil \u20ac", "age": "32", "date_of_birth": "23/09/1988", "nation": "Su\u00e9cia", "contract_expires": "-"}, {"name": "Jean Barrientos", "position": "Meia Ofensivo", "number": "14", "market_value": "350 mil \u20ac", "age": "30", "date_of_birth": "16/09/1990", "nation": "Uruguai", "contract_expires": "30/06/2022"}, {"name": "Nicol\u00e1s Mart\u00ednez", "position": "Meia Ofensivo", "number": "12", "market_value": "300 mil \u20ac", "age": "33", "date_of_birth": "25/09/1987", "nation": "Argentina", "contract_expires": "30/06/2021"}, {"name": "Sotiris Ninis", "position": "Meia Ofensivo", "number": "8", "market_value": "200 mil \u20ac", "age": "30", "date_of_birth": "03/04/1990", "nation": "Gr\u00e9cia", "contract_expires": "30/06/2021"}, {"name": "Georgios Ballas", "position": "Atacante", "number": "25", "market_value": "-\u00a0\u20ac", "age": "19", "date_of_birth": "07/04/2001", "nation": "Gr\u00e9cia", "contract_expires": "-"}, {"name": "Iker Guarrotxena", "position": "Ponta esquerda", "number": "10", "market_value": "450 mil \u20ac", "age": "27", "date_of_birth": "06/12/1992", "nation": "Espanha", "contract_expires": "30/06/2021"}, {"name": "Juli\u00e1n Bartolo", "position": "Ponta esquerda", "number": "73", "market_value": "100 mil \u20ac", "age": "24", "date_of_birth": "15/04/1996", "nation": "Argentina", "contract_expires": "30/06/2021"}, {"name": "Anastasios Kritikos", "position": "Ponta Direita", "number": "7", "market_value": "300 mil \u20ac", "age": "25", "date_of_birth": "25/01/1995", "nation": "Gr\u00e9cia", "contract_expires": "30/06/2022"}, {"name": "Juan Jos\u00e9 Perea", "position": "Centroavante", "number": "19", "market_value": "500 mil \u20ac", "age": "20", "date_of_birth": "23/02/2000", "nation": "Col\u00f4mbia", "contract_expires": "30/06/2021"}, {"name": "Anastasios Douvikas", "position": "Centroavante", "number": "9", "market_value": "250 mil \u20ac", "age": "21", "date_of_birth": "02/08/1999", "nation": "Gr\u00e9cia", "contract_expires": "-"}, {"name": "Erik Jendrisek", "position": "Centroavante", "number": "26", "market_value": "250 mil \u20ac", "age": "33", "date_of_birth": "26/10/1986", "nation": "Eslov\u00e1quia", "contract_expires": "30/06/2021"}]}, {"name": "ApollonSmyrnis", "amount_of_players": "27", "media_age": "27,7", "market_value": "6,10 milh\u00f5es \u20ac", "manager": {"name": "Georgios Paraschos", "nation": "Gr\u00e9cia", "age": "68", "contract_expires": "30/06/2021", "since": "10/09/2020"}, "players": [{"name": "Davino Verhulst", "position": "Goleiro", "number": "-", "market_value": "300 mil \u20ac", "age": "32", "date_of_birth": "25/11/1987", "nation": "B\u00e9lgica", "contract_expires": "30/06/2021"}, {"name": "Konstantinos Kotsaris", "position": "Goleiro", "number": "-", "market_value": "300 mil \u20ac", "age": "24", "date_of_birth": "25/07/1996", "nation": "Gr\u00e9cia", "contract_expires": "-"}, {"name": "Adil Rhaili", "position": "Zagueiro", "number": "-", "market_value": "400 mil \u20ac", "age": "29", "date_of_birth": "25/04/1991", "nation": "Marrocos", "contract_expires": "30/06/2021"}, {"name": "Domingues", "position": "Zagueiro", "number": "-", "market_value": "250 mil \u20ac", "age": "31", "date_of_birth": "28/09/1988", "nation": "Brasil", "contract_expires": "30/06/2021"}, {"name": "Christos Lisgaras", "position": "Zagueiro", "number": "-", "market_value": "150 mil \u20ac", "age": "34", "date_of_birth": "12/02/1986", "nation": "Gr\u00e9cia", "contract_expires": "30/06/2021"}, {"name": "Diamantis Chouchoumis", "position": "Lateral Esq.", "number": "-", "market_value": "200 mil \u20ac", "age": "26", "date_of_birth": "17/07/1994", "nation": "Gr\u00e9cia", "contract_expires": "30/06/2021"}, {"name": "Vasilios Vitlis", "position": "Lateral Esq.", "number": "-", "market_value": "200 mil \u20ac", "age": "26", "date_of_birth": "28/10/1993", "nation": "Gr\u00e9cia", "contract_expires": "30/06/2021"}, {"name": "Dimosthenis Baxevanidis", "position": "Lateral Dir.", "number": "-", "market_value": "250 mil \u20ac", "age": "32", "date_of_birth": "14/04/1988", "nation": "Gr\u00e9cia", "contract_expires": "30/06/2021"}, {"name": "Savvas Tsabouris", "position": "Lateral Dir.", "number": "-", "market_value": "200 mil \u20ac", "age": "34", "date_of_birth": "16/07/1986", "nation": "Gr\u00e9cia", "contract_expires": "30/06/2021"}, {"name": "Giannis Varkas", "position": "Lateral Dir.", "number": "-", "market_value": "200 mil \u20ac", "age": "22", "date_of_birth": "27/03/1998", "nation": "Gr\u00e9cia", "contract_expires": "30/06/2022"}, {"name": "Fatjon Andoni", "position": "Volante", "number": "-", "market_value": "350 mil \u20ac", "age": "29", "date_of_birth": "19/06/1991", "nation": "Alb\u00e2nia", "contract_expires": "30/06/2021"}, {"name": "Anastasios Lagos", "position": "Volante", "number": "-", "market_value": "200 mil \u20ac", "age": "28", "date_of_birth": "12/04/1992", "nation": "Gr\u00e9cia", "contract_expires": "30/06/2021"}, {"name": "Vykintas Slivka", "position": "Meia central", "number": "-", "market_value": "300 mil \u20ac", "age": "25", "date_of_birth": "29/04/1995", "nation": "Litu\u00e2nia", "contract_expires": "30/06/2022"}, {"name": "Manolis Patralis", "position": "Meia central", "number": "-", "market_value": "300 mil \u20ac", "age": "23", "date_of_birth": "06/02/1997", "nation": "Gr\u00e9cia", "contract_expires": "30/06/2022"}, {"name": "Marko Blazic", "position": "Meia central", "number": "-", "market_value": "200 mil \u20ac", "age": "35", "date_of_birth": "02/08/1985", "nation": "S\u00e9rvia", "contract_expires": "30/06/2021"}, {"name": "Leonidas Rossi", "position": "Meia Esquerda", "number": "-", "market_value": "200 mil \u20ac", "age": "21", "date_of_birth": "19/04/1999", "nation": "Gr\u00e9cia", "contract_expires": "30/06/2021"}, {"name": "Israel Coll", "position": "Meia Ofensivo", "number": "-", "market_value": "200 mil \u20ac", "age": "27", "date_of_birth": "22/07/1993", "nation": "Argentina", "contract_expires": "30/06/2021"}, {"name": "Charalampos Pavlidis", "position": "Meia Ofensivo", "number": "-", "market_value": "150 mil \u20ac", "age": "29", "date_of_birth": "06/05/1991", "nation": "Gr\u00e9cia", "contract_expires": "30/06/2021"}, {"name": "Manolis Kragiopoulos", "position": "Meia Ofensivo", "number": "-", "market_value": "-\u00a0\u20ac", "age": "22", "date_of_birth": "29/05/1998", "nation": "Gr\u00e9cia", "contract_expires": "-"}, {"name": "Georgios Rodis", "position": "Atacante", "number": "-", "market_value": "-\u00a0\u20ac", "age": "18", "date_of_birth": "02/11/2001", "nation": "Gr\u00e9cia", "contract_expires": "-"}, {"name": "Marc Fern\u00e1ndez", "position": "Ponta esquerda", "number": "-", "market_value": "400 mil \u20ac", "age": "30", "date_of_birth": "29/04/1990", "nation": "Espanha", "contract_expires": "30/06/2022"}, {"name": "Thom\u00e1s Bedinelli", "position": "Ponta esquerda", "number": "-", "market_value": "300 mil \u20ac", "age": "27", "date_of_birth": "24/02/1993", "nation": "Brasil", "contract_expires": "30/06/2021"}, {"name": "Sotiris Tsiloulis", "position": "Ponta Direita", "number": "-", "market_value": "450 mil \u20ac", "age": "25", "date_of_birth": "14/02/1995", "nation": "Gr\u00e9cia", "contract_expires": "-"}, {"name": "Athanasios Karagounis", "position": "Ponta Direita", "number": "-", "market_value": "200 mil \u20ac", "age": "29", "date_of_birth": "25/09/1991", "nation": "Gr\u00e9cia", "contract_expires": "30/06/2021"}, {"name": "Theodoros Chiritrantas", "position": "Ponta Direita", "number": "-", "market_value": "-\u00a0\u20ac", "age": "19", "date_of_birth": "10/11/2000", "nation": "Gr\u00e9cia", "contract_expires": "-"}, {"name": "Abiola Dauda", "position": "Centroavante", "number": "-", "market_value": "250 mil \u20ac", "age": "32", "date_of_birth": "03/02/1988", "nation": "Nig\u00e9ria", "contract_expires": "30/06/2021"}, {"name": "Nikolaos Ioannidis", "position": "Centroavante", "number": "-", "market_value": "150 mil \u20ac", "age": "26", "date_of_birth": "26/04/1994", "nation": "Gr\u00e9cia", "contract_expires": "30/06/2021"}]}, {"name": "OlympiacosPireu", "amount_of_players": "35", "media_age": "26,3", "market_value": "84,75 milh\u00f5es \u20ac", "manager": {"name": "Pedro Martins", "nation": "Portugal", "age": "50", "contract_expires": "30/06/2022", "since": "01/07/2018"}, "players": [{"name": "Jos\u00e9 S\u00e1", "position": "Goleiro", "number": "1", "market_value": "6,00 milh\u00f5es \u20ac", "age": "27", "date_of_birth": "17/01/1993", "nation": "Portugal", "contract_expires": "30/06/2023"}, {"name": "Bobby Allain", "position": "Goleiro", "number": "16", "market_value": "600 mil \u20ac", "age": "28", "date_of_birth": "28/11/1991", "nation": "Fran\u00e7a", "contract_expires": "30/06/2021"}, {"name": "\u00d6gmundur Kristinsson", "position": "Goleiro", "number": "31", "market_value": "600 mil \u20ac", "age": "31", "date_of_birth": "19/06/1989", "nation": "Isl\u00e2ndia", "contract_expires": "30/06/2023"}, {"name": "Marios Siabanis", "position": "Goleiro", "number": "99", "market_value": "250 mil \u20ac", "age": "20", "date_of_birth": "28/09/1999", "nation": "Gr\u00e9cia", "contract_expires": "30/06/2023"}, {"name": "Ilias Karargyris", "position": "Goleiro", "number": "44", "market_value": "150 mil \u20ac", "age": "18", "date_of_birth": "29/06/2002", "nation": "Gr\u00e9cia", "contract_expires": "30/06/2022"}, {"name": "Konstantinos Tzolakis", "position": "Goleiro", "number": "88", "market_value": "150 mil \u20ac", "age": "17", "date_of_birth": "08/11/2002", "nation": "Gr\u00e9cia", "contract_expires": "-"}, {"name": "R\u00faben Semedo", "position": "Zagueiro", "number": "3", "market_value": "7,00 milh\u00f5es \u20ac", "age": "26", "date_of_birth": "04/04/1994", "nation": "Portugal", "contract_expires": "30/06/2023"}, {"name": "Pape Abou Ciss\u00e9", "position": "Zagueiro", "number": "66", "market_value": "5,00 milh\u00f5es \u20ac", "age": "25", "date_of_birth": "14/09/1995", "nation": "Senegal", "contract_expires": "30/06/2022"}, {"name": "Ousseynou Ba", "position": "Zagueiro", "number": "24", "market_value": "4,00 milh\u00f5es \u20ac", "age": "24", "date_of_birth": "11/11/1995", "nation": "Senegal", "contract_expires": "30/06/2023"}, {"name": "Svetozar Markovic", "position": "Zagueiro", "number": "15", "market_value": "1,00 milh\u00f5es \u20ac", "age": "20", "date_of_birth": "23/03/2000", "nation": "S\u00e9rvia", "contract_expires": "30/06/2024"}, {"name": "Avraam Papadopoulos", "position": "Zagueiro", "number": "34", "market_value": "300 mil \u20ac", "age": "35", "date_of_birth": "03/12/1984", "nation": "Gr\u00e9cia", "contract_expires": "30/06/2021"}, {"name": "Leonardo Koutris", "position": "Lateral Esq.", "number": "23", "market_value": "3,50 milh\u00f5es \u20ac", "age": "25", "date_of_birth": "23/07/1995", "nation": "Gr\u00e9cia", "contract_expires": "-"}, {"name": "Jose Cholevas", "position": "Lateral Esq.", "number": "25", "market_value": "1,20 milh\u00f5es \u20ac", "age": "36", "date_of_birth": "27/06/1984", "nation": "Gr\u00e9cia", "contract_expires": "30/06/2021"}, {"name": "Apostolos Apostolopoulos", "position": "Lateral Esq.", "number": "26", "market_value": "-\u00a0\u20ac", "age": "17", "date_of_birth": "11/12/2002", "nation": "Gr\u00e9cia", "contract_expires": "30/06/2023"}, {"name": "Rafinha", "position": "Lateral Dir.", "number": "13", "market_value": "2,40 milh\u00f5es \u20ac", "age": "35", "date_of_birth": "07/09/1985", "nation": "Brasil", "contract_expires": "30/06/2022"}, {"name": "Yann M'Vila", "position": "Volante", "number": "6", "market_value": "6,00 milh\u00f5es \u20ac", "age": "30", "date_of_birth": "29/06/1990", "nation": "Fran\u00e7a", "contract_expires": "30/06/2023"}, {"name": "Mady Camara", "position": "Meia central", "number": "4", "market_value": "12,00 milh\u00f5es \u20ac", "age": "23", "date_of_birth": "28/02/1997", "nation": "Guin\u00e9", "contract_expires": "30/06/2023"}, {"name": "Andreas Bouchalakis", "position": "Meia central", "number": "5", "market_value": "3,00 milh\u00f5es \u20ac", "age": "27", "date_of_birth": "05/04/1993", "nation": "Gr\u00e9cia", "contract_expires": "30/06/2022"}, {"name": "P\u00eap\u00ea", "position": "Meia central", "number": "10", "market_value": "3,00 milh\u00f5es \u20ac", "age": "23", "date_of_birth": "20/05/1997", "nation": "Portugal", "contract_expires": "30/06/2024"}, {"name": "Caf\u00fa", "position": "Meia central", "number": "8", "market_value": "1,20 milh\u00f5es \u20ac", "age": "27", "date_of_birth": "26/02/1993", "nation": "Portugal", "contract_expires": "30/06/2023"}, {"name": "Ioannis Kosti", "position": "Meia central", "number": "-", "market_value": "625 mil \u20ac", "age": "20", "date_of_birth": "17/03/2000", "nation": "Chipre", "contract_expires": "30/06/2025"}, {"name": "Athanasios Androutsos", "position": "Meia central", "number": "14", "market_value": "600 mil \u20ac", "age": "23", "date_of_birth": "06/05/1997", "nation": "Gr\u00e9cia", "contract_expires": "30/06/2021"}, {"name": "Alexandros Nikolias", "position": "Meia central", "number": "-", "market_value": "475 mil \u20ac", "age": "26", "date_of_birth": "23/07/1994", "nation": "Gr\u00e9cia", "contract_expires": "30/06/2022"}, {"name": "Konstantinos Fortounis", "position": "Meia Ofensivo", "number": "7", "market_value": "8,00 milh\u00f5es \u20ac", "age": "27", "date_of_birth": "16/10/1992", "nation": "Gr\u00e9cia", "contract_expires": "30/06/2023"}, {"name": "Mathieu Valbuena", "position": "Meia Ofensivo", "number": "28", "market_value": "1,00 milh\u00f5es \u20ac", "age": "35", "date_of_birth": "28/09/1984", "nation": "Fran\u00e7a", "contract_expires": "30/06/2021"}, {"name": "Georgios Masouras", "position": "Ponta esquerda", "number": "19", "market_value": "3,00 milh\u00f5es \u20ac", "age": "26", "date_of_birth": "01/01/1994", "nation": "Gr\u00e9cia", "contract_expires": "30/06/2022"}, {"name": "Lazar Randjelovic", "position": "Ponta Direita", "number": "97", "market_value": "1,80 milh\u00f5es \u20ac", "age": "23", "date_of_birth": "05/08/1997", "nation": "S\u00e9rvia", "contract_expires": "30/06/2023"}, {"name": "El Arbi Hillel Soudani", "position": "Ponta Direita", "number": "2", "market_value": "1,00 milh\u00f5es \u20ac", "age": "32", "date_of_birth": "25/11/1987", "nation": "Arg\u00e9lia", "contract_expires": "30/06/2021"}, {"name": "Marios Vrousai", "position": "Ponta Direita", "number": "17", "market_value": "900 mil \u20ac", "age": "22", "date_of_birth": "02/07/1998", "nation": "Gr\u00e9cia", "contract_expires": "30/06/2021"}, {"name": "Bruno", "position": "Ponta Direita", "number": "18", "market_value": "500 mil \u20ac", "age": "26", "date_of_birth": "26/05/1994", "nation": "Brasil", "contract_expires": "30/06/2022"}, {"name": "Georgios Manthatis", "position": "Ponta Direita", "number": "-", "market_value": "350 mil \u20ac", "age": "23", "date_of_birth": "11/05/1997", "nation": "Gr\u00e9cia", "contract_expires": "30/06/2021"}, {"name": "Maximiliano Lovera", "position": "Atacante", "number": "22", "market_value": "2,80 milh\u00f5es \u20ac", "age": "21", "date_of_birth": "09/03/1999", "nation": "Argentina", "contract_expires": "30/06/2024"}, {"name": "Youssef El Arabi", "position": "Centroavante", "number": "11", "market_value": "3,00 milh\u00f5es \u20ac", "age": "33", "date_of_birth": "03/02/1987", "nation": "Marrocos", "contract_expires": "30/06/2021"}, {"name": "Ahmed Hassan", "position": "Centroavante", "number": "9", "market_value": "2,80 milh\u00f5es \u20ac", "age": "27", "date_of_birth": "05/03/1993", "nation": "Egito", "contract_expires": "30/06/2023"}, {"name": "Hugo Cuypers", "position": "Centroavante", "number": "20", "market_value": "550 mil \u20ac", "age": "23", "date_of_birth": "07/02/1997", "nation": "B\u00e9lgica", "contract_expires": "30/06/2022"}]}, {"name": "AEKAtenas", "amount_of_players": "42", "media_age": "24,7", "market_value": "35,30 milh\u00f5es \u20ac", "manager": {"name": "Massimo Carrera", "nation": "It\u00e1lia", "age": "56", "contract_expires": "30/06/2021", "since": "08/12/2019"}, "players": [{"name": "Panagiotis Tsintotas", "position": "Goleiro", "number": "1", "market_value": "500 mil \u20ac", "age": "27", "date_of_birth": "04/07/1993", "nation": "Gr\u00e9cia", "contract_expires": "30/06/2023"}, {"name": "Georgios Athanasiadis", "position": "Goleiro", "number": "30", "market_value": "400 mil \u20ac", "age": "27", "date_of_birth": "07/04/1993", "nation": "Gr\u00e9cia", "contract_expires": "30/06/2023"}, {"name": "Vasilios Chatziemmanouil", "position": "Goleiro", "number": "16", "market_value": "-\u00a0\u20ac", "age": "21", "date_of_birth": "09/08/1999", "nation": "Gr\u00e9cia", "contract_expires": "30/06/2025"}, {"name": "Georgios Theocharis", "position": "Goleiro", "number": "99", "market_value": "-\u00a0\u20ac", "age": "18", "date_of_birth": "30/06/2002", "nation": "Gr\u00e9cia", "contract_expires": "30/06/2024"}, {"name": "Nassim Hnid", "position": "Zagueiro", "number": "26", "market_value": "725 mil \u20ac", "age": "23", "date_of_birth": "12/03/1997", "nation": "Tun\u00edsia", "contract_expires": "30/06/2024"}, {"name": "Stratos Svarnas", "position": "Zagueiro", "number": "24", "market_value": "700 mil \u20ac", "age": "22", "date_of_birth": "11/11/1997", "nation": "Gr\u00e9cia", "contract_expires": "30/06/2025"}, {"name": "Dmytro Chygrynskyi", "position": "Zagueiro", "number": "19", "market_value": "500 mil \u20ac", "age": "33", "date_of_birth": "07/11/1986", "nation": "Ucr\u00e2nia", "contract_expires": "30/06/2021"}, {"name": "Ziga Laci", "position": "Zagueiro", "number": "15", "market_value": "200 mil \u20ac", "age": "18", "date_of_birth": "20/07/2002", "nation": "Eslov\u00e9nia", "contract_expires": "30/06/2023"}, {"name": "Michalis Bousis", "position": "Zagueiro", "number": "-", "market_value": "-\u00a0\u20ac", "age": "21", "date_of_birth": "02/01/1999", "nation": "Gr\u00e9cia", "contract_expires": "30/06/2021"}, {"name": "Mario Mitaj", "position": "Zagueiro", "number": "40", "market_value": "-\u00a0\u20ac", "age": "17", "date_of_birth": "06/08/2003", "nation": "Alb\u00e2nia", "contract_expires": "30/06/2023"}, {"name": "H\u00e9lder Lopes", "position": "Lateral Esq.", "number": "3", "market_value": "600 mil \u20ac", "age": "31", "date_of_birth": "04/01/1989", "nation": "Portugal", "contract_expires": "30/06/2022"}, {"name": "Emanuel Ins\u00faa", "position": "Lateral Esq.", "number": "22", "market_value": "600 mil \u20ac", "age": "29", "date_of_birth": "10/04/1991", "nation": "Argentina", "contract_expires": "30/06/2023"}, {"name": "Georgios Giannoutsos", "position": "Lateral Esq.", "number": "33", "market_value": "200 mil \u20ac", "age": "22", "date_of_birth": "16/07/1998", "nation": "Gr\u00e9cia", "contract_expires": "30/06/2021"}, {"name": "Michalis Bakakis", "position": "Lateral Dir.", "number": "2", "market_value": "1,00 milh\u00f5es \u20ac", "age": "29", "date_of_birth": "18/03/1991", "nation": "Gr\u00e9cia", "contract_expires": "30/06/2023"}, {"name": "Paulinho", "position": "Lateral Dir.", "number": "27", "market_value": "800 mil \u20ac", "age": "29", "date_of_birth": "13/07/1991", "nation": "Portugal", "contract_expires": "30/06/2021"}, {"name": "Stavros Vasilantonopoulos", "position": "Lateral Dir.", "number": "88", "market_value": "325 mil \u20ac", "age": "28", "date_of_birth": "28/01/1992", "nation": "Gr\u00e9cia", "contract_expires": "30/06/2021"}, {"name": "Konstantinos Stamoulis", "position": "Lateral Dir.", "number": "31", "market_value": "50 mil \u20ac", "age": "19", "date_of_birth": "29/10/2000", "nation": "Gr\u00e9cia", "contract_expires": "30/06/2022"}, {"name": "Vedad Radonja", "position": "Lateral Dir.", "number": "37", "market_value": "-\u00a0\u20ac", "age": "19", "date_of_birth": "06/09/2001", "nation": "B\u00f3snia-Herzegovina", "contract_expires": "30/06/2024"}, {"name": "Andr\u00e9 Sim\u00f5es", "position": "Volante", "number": "8", "market_value": "1,50 milh\u00f5es \u20ac", "age": "30", "date_of_birth": "16/12/1989", "nation": "Portugal", "contract_expires": "30/06/2022"}, {"name": "Anel Sabanadzovic", "position": "Volante", "number": "44", "market_value": "400 mil \u20ac", "age": "21", "date_of_birth": "24/05/1999", "nation": "B\u00f3snia-Herzegovina", "contract_expires": "31/12/2023"}, {"name": "Konstantinos Galanopoulos", "position": "Meia central", "number": "25", "market_value": "2,50 milh\u00f5es \u20ac", "age": "22", "date_of_birth": "28/12/1997", "nation": "Gr\u00e9cia", "contract_expires": "30/06/2023"}, {"name": "Nenad Krsticic", "position": "Meia central", "number": "6", "market_value": "1,80 milh\u00f5es \u20ac", "age": "30", "date_of_birth": "03/07/1990", "nation": "S\u00e9rvia", "contract_expires": "30/06/2022"}, {"name": "Damian Szymanski", "position": "Meia central", "number": "5", "market_value": "1,50 milh\u00f5es \u20ac", "age": "25", "date_of_birth": "16/06/1995", "nation": "Pol\u00f3nia", "contract_expires": "30/06/2024"}, {"name": "David Sim\u00e3o", "position": "Meia central", "number": "28", "market_value": "300 mil \u20ac", "age": "30", "date_of_birth": "15/05/1990", "nation": "Portugal", "contract_expires": "30/06/2022"}, {"name": "Paris Babis", "position": "Meia central", "number": "23", "market_value": "100 mil \u20ac", "age": "21", "date_of_birth": "17/07/1999", "nation": "Gr\u00e9cia", "contract_expires": "30/06/2022"}, {"name": "Petros Mantalos", "position": "Meia Ofensivo", "number": "20", "market_value": "4,00 milh\u00f5es \u20ac", "age": "29", "date_of_birth": "31/08/1991", "nation": "Gr\u00e9cia", "contract_expires": "30/06/2022"}, {"name": "Yevgen Shakhov", "position": "Meia Ofensivo", "number": "28", "market_value": "1,50 milh\u00f5es \u20ac", "age": "29", "date_of_birth": "30/11/1990", "nation": "Ucr\u00e2nia", "contract_expires": "30/06/2022"}, {"name": "Giannis-Fivos Botos", "position": "Meia Ofensivo", "number": "70", "market_value": "200 mil \u20ac", "age": "19", "date_of_birth": "20/12/2000", "nation": "Gr\u00e9cia", "contract_expires": "30/06/2023"}, {"name": "Giannis Sardelis", "position": "Meia Ofensivo", "number": "51", "market_value": "100 mil \u20ac", "age": "19", "date_of_birth": "03/11/2000", "nation": "Gr\u00e9cia", "contract_expires": "30/06/2021"}, {"name": "Levi Garc\u00eda", "position": "Ponta esquerda", "number": "9", "market_value": "1,80 milh\u00f5es \u20ac", "age": "22", "date_of_birth": "20/11/1997", "nation": "Trinidad e Tobago", "contract_expires": "30/06/2025"}, {"name": "Christos Albanis", "position": "Ponta esquerda", "number": "14", "market_value": "600 mil \u20ac", "age": "25", "date_of_birth": "05/11/1994", "nation": "Gr\u00e9cia", "contract_expires": "30/06/2021"}, {"name": "Milos Deletic", "position": "Ponta esquerda", "number": "32", "market_value": "500 mil \u20ac", "age": "26", "date_of_birth": "14/10/1993", "nation": "S\u00e9rvia", "contract_expires": "30/06/2022"}, {"name": "Petar Karaklajic", "position": "Ponta esquerda", "number": "69", "market_value": "150 mil \u20ac", "age": "20", "date_of_birth": "01/02/2000", "nation": "S\u00e9rvia", "contract_expires": "30/06/2025"}, {"name": "Theodosis Macheras", "position": "Ponta esquerda", "number": "53", "market_value": "-\u00a0\u20ac", "age": "20", "date_of_birth": "09/05/2000", "nation": "Gr\u00e9cia", "contract_expires": "30/06/2023"}, {"name": "Daniele Verde", "position": "Ponta Direita", "number": "7", "market_value": "1,20 milh\u00f5es \u20ac", "age": "24", "date_of_birth": "20/06/1996", "nation": "It\u00e1lia", "contract_expires": "30/06/2022"}, {"name": "Christos Giousis", "position": "Ponta Direita", "number": "77", "market_value": "150 mil \u20ac", "age": "21", "date_of_birth": "08/02/1999", "nation": "Gr\u00e9cia", "contract_expires": "30/06/2023"}, {"name": "Marko Livaja", "position": "Centroavante", "number": "10", "market_value": "4,50 milh\u00f5es \u20ac", "age": "27", "date_of_birth": "26/08/1993", "nation": "Cro\u00e1cia", "contract_expires": "30/06/2021"}, {"name": "N\u00e9lson Oliveira", "position": "Centroavante", "number": "18", "market_value": "4,00 milh\u00f5es \u20ac", "age": "29", "date_of_birth": "08/08/1991", "nation": "Portugal", "contract_expires": "30/06/2021"}, {"name": "Karim Ansarifard", "position": "Centroavante", "number": "11", "market_value": "1,20 milh\u00f5es \u20ac", "age": "30", "date_of_birth": "03/04/1990", "nation": "Ir\u00e3o", "contract_expires": "30/06/2023"}, {"name": "Bright Enobakhare", "position": "Centroavante", "number": "12", "market_value": "450 mil \u20ac", "age": "22", "date_of_birth": "08/02/1998", "nation": "Nig\u00e9ria", "contract_expires": "30/06/2023"}, {"name": "Giannis Iatroudis", "position": "Centroavante", "number": "17", "market_value": "250 mil \u20ac", "age": "21", "date_of_birth": "02/02/1999", "nation": "Gr\u00e9cia", "contract_expires": "30/06/2024"}, {"name": "Efthymios Christopoulos", "position": "Centroavante", "number": "52", "market_value": "-\u00a0\u20ac", "age": "20", "date_of_birth": "20/09/2000", "nation": "Gr\u00e9cia", "contract_expires": "30/06/2023"}]}, {"name": "PanathinaikosAtenas", "amount_of_players": "35", "media_age": "23,9", "market_value": "22,28 milh\u00f5es \u20ac", "manager": {"name": "Dani Poyatos", "nation": "Espanha", "age": "42", "contract_expires": "30/06/2022", "since": "21/07/2020"}, "players": [{"name": "Sokratis Dioudis", "position": "Goleiro", "number": "1", "market_value": "900 mil \u20ac", "age": "27", "date_of_birth": "03/02/1993", "nation": "Gr\u00e9cia", "contract_expires": "30/06/2023"}, {"name": "Vasilios Xenopoulos", "position": "Goleiro", "number": "15", "market_value": "200 mil \u20ac", "age": "22", "date_of_birth": "20/05/1998", "nation": "Gr\u00e9cia", "contract_expires": "30/06/2021"}, {"name": "Nikolaos Christogeorgos", "position": "Goleiro", "number": "68", "market_value": "100 mil \u20ac", "age": "20", "date_of_birth": "03/01/2000", "nation": "Gr\u00e9cia", "contract_expires": "30/06/2021"}, {"name": "Christos Chatzigiannakis", "position": "Goleiro", "number": "61", "market_value": "-\u00a0\u20ac", "age": "18", "date_of_birth": "09/03/2002", "nation": "Gr\u00e9cia", "contract_expires": "30/06/2023"}, {"name": "Bart Schenkeveld", "position": "Zagueiro", "number": "5", "market_value": "800 mil \u20ac", "age": "29", "date_of_birth": "28/08/1991", "nation": "Holanda", "contract_expires": "30/06/2021"}, {"name": "Fran V\u00e9lez", "position": "Zagueiro", "number": "4", "market_value": "600 mil \u20ac", "age": "29", "date_of_birth": "23/06/1991", "nation": "Espanha", "contract_expires": "30/06/2022"}, {"name": "Achilleas Poungouras", "position": "Zagueiro", "number": "44", "market_value": "600 mil \u20ac", "age": "24", "date_of_birth": "13/12/1995", "nation": "Gr\u00e9cia", "contract_expires": "30/06/2023"}, {"name": "Theofanis Mavrommatis", "position": "Zagueiro", "number": "24", "market_value": "300 mil \u20ac", "age": "23", "date_of_birth": "16/01/1997", "nation": "Gr\u00e9cia", "contract_expires": "30/06/2022"}, {"name": "Dimitrios Karagiannis", "position": "Zagueiro", "number": "38", "market_value": "-\u00a0\u20ac", "age": "19", "date_of_birth": "27/02/2001", "nation": "Gr\u00e9cia", "contract_expires": "30/06/2021"}, {"name": "Juankar", "position": "Lateral Esq.", "number": "3", "market_value": "800 mil \u20ac", "age": "30", "date_of_birth": "30/03/1990", "nation": "Espanha", "contract_expires": "30/06/2022"}, {"name": "Ilias Chatzitheodoridis", "position": "Lateral Esq.", "number": "12", "market_value": "400 mil \u20ac", "age": "22", "date_of_birth": "05/11/1997", "nation": "Gr\u00e9cia", "contract_expires": "30/06/2023"}, {"name": "Vasilios Zagaritis", "position": "Lateral Esq.", "number": "47", "market_value": "150 mil \u20ac", "age": "19", "date_of_birth": "04/05/2001", "nation": "Gr\u00e9cia", "contract_expires": "30/06/2021"}, {"name": "Konstantinos Lazaridis", "position": "Lateral Esq.", "number": "16", "market_value": "-\u00a0\u20ac", "age": "17", "date_of_birth": "26/12/2002", "nation": "Gr\u00e9cia", "contract_expires": "-"}, {"name": "Facundo S\u00e1nchez", "position": "Lateral Dir.", "number": "14", "market_value": "1,60 milh\u00f5es \u20ac", "age": "30", "date_of_birth": "07/03/1990", "nation": "Argentina", "contract_expires": "30/06/2022"}, {"name": "Dimitrios Kourbelis", "position": "Volante", "number": "21", "market_value": "1,80 milh\u00f5es \u20ac", "age": "26", "date_of_birth": "02/11/1993", "nation": "Gr\u00e9cia", "contract_expires": "30/06/2023"}, {"name": "Sotiris Alexandropoulos", "position": "Volante", "number": "55", "market_value": "150 mil \u20ac", "age": "18", "date_of_birth": "26/11/2001", "nation": "Gr\u00e9cia", "contract_expires": "30/06/2022"}, {"name": "Yassin Ayoub", "position": "Meia central", "number": "8", "market_value": "1,20 milh\u00f5es \u20ac", "age": "26", "date_of_birth": "06/03/1994", "nation": "Marrocos", "contract_expires": "30/06/2023"}, {"name": "Adriano Skenterai", "position": "Meia central", "number": "-", "market_value": "-\u00a0\u20ac", "age": "20", "date_of_birth": "26/04/2000", "nation": "Gr\u00e9cia", "contract_expires": "30/06/2022"}, {"name": "Giannis Bouzoukis", "position": "Meia Ofensivo", "number": "18", "market_value": "1,50 milh\u00f5es \u20ac", "age": "22", "date_of_birth": "27/03/1998", "nation": "Gr\u00e9cia", "contract_expires": "30/06/2022"}, {"name": "Lucas Villafa\u00f1ez", "position": "Meia Ofensivo", "number": "19", "market_value": "1,20 milh\u00f5es \u20ac", "age": "28", "date_of_birth": "04/10/1991", "nation": "Argentina", "contract_expires": "30/06/2022"}, {"name": "Andreas Athanasakopoulos", "position": "Meia Ofensivo", "number": "37", "market_value": "150 mil \u20ac", "age": "18", "date_of_birth": "27/11/2001", "nation": "Gr\u00e9cia", "contract_expires": "30/06/2022"}, {"name": "Dimitrios Serpezis", "position": "Meia Ofensivo", "number": "20", "market_value": "100 mil \u20ac", "age": "19", "date_of_birth": "14/03/2001", "nation": "Gr\u00e9cia", "contract_expires": "30/06/2022"}, {"name": "Xavier", "position": "Ponta esquerda", "number": "7", "market_value": "800 mil \u20ac", "age": "28", "date_of_birth": "06/07/1992", "nation": "Portugal", "contract_expires": "30/06/2023"}, {"name": "Yohan Mollo", "position": "Ponta esquerda", "number": "-", "market_value": "475 mil \u20ac", "age": "31", "date_of_birth": "18/07/1989", "nation": "Fran\u00e7a", "contract_expires": "30/06/2021"}, {"name": "Spyros Tzavidas", "position": "Ponta esquerda", "number": "77", "market_value": "-\u00a0\u20ac", "age": "19", "date_of_birth": "21/08/2001", "nation": "Gr\u00e9cia", "contract_expires": "30/06/2022"}, {"name": "Anastasios Chatzigiovanis", "position": "Ponta Direita", "number": "11", "market_value": "2,00 milh\u00f5es \u20ac", "age": "23", "date_of_birth": "31/05/1997", "nation": "Gr\u00e9cia", "contract_expires": "30/06/2022"}, {"name": "Aitor Cantalapiedra", "position": "Ponta Direita", "number": "22", "market_value": "1,60 milh\u00f5es \u20ac", "age": "24", "date_of_birth": "10/02/1996", "nation": "Espanha", "contract_expires": "30/06/2023"}, {"name": "Dimitrios Emmanouilidis", "position": "Ponta Direita", "number": "17", "market_value": "700 mil \u20ac", "age": "19", "date_of_birth": "24/10/2000", "nation": "Gr\u00e9cia", "contract_expires": "30/06/2022"}, {"name": "Uffe Bech", "position": "Ponta Direita", "number": "-", "market_value": "300 mil \u20ac", "age": "27", "date_of_birth": "13/01/1993", "nation": "Dinamarca", "contract_expires": "30/06/2022"}, {"name": "Carlitos", "position": "Centroavante", "number": "10", "market_value": "1,60 milh\u00f5es \u20ac", "age": "30", "date_of_birth": "12/06/1990", "nation": "Espanha", "contract_expires": "30/06/2023"}, {"name": "Federico Macheda", "position": "Centroavante", "number": "9", "market_value": "1,50 milh\u00f5es \u20ac", "age": "29", "date_of_birth": "22/08/1991", "nation": "It\u00e1lia", "contract_expires": "30/06/2023"}, {"name": "Fotis Ioannidis", "position": "Centroavante", "number": "27", "market_value": "300 mil \u20ac", "age": "20", "date_of_birth": "10/01/2000", "nation": "Gr\u00e9cia", "contract_expires": "30/06/2024"}, {"name": "Argyris Kampetsis", "position": "Centroavante", "number": "99", "market_value": "300 mil \u20ac", "age": "21", "date_of_birth": "06/05/1999", "nation": "Gr\u00e9cia", "contract_expires": "30/06/2021"}, {"name": "Kristo Shehu", "position": "Centroavante", "number": "-", "market_value": "150 mil \u20ac", "age": "20", "date_of_birth": "01/03/2000", "nation": "Gr\u00e9cia", "contract_expires": "30/06/2022"}, {"name": "Christian Konan", "position": "Centroavante", "number": "-", "market_value": "-\u00a0\u20ac", "age": "21", "date_of_birth": "12/07/1999", "nation": "It\u00e1lia", "contract_expires": "30/06/2022"}]}, {"name": "AtromitosAthen", "amount_of_players": "25", "media_age": "27,0", "market_value": "10,70 milh\u00f5es \u20ac", "manager": {"name": "Damir Canadi", "nation": "\u00c1ustria", "age": "50", "contract_expires": "30/06/2022", "since": "29/07/2020"}, "players": [{"name": "Andreas Gianniotis", "position": "Goleiro", "number": "22", "market_value": "600 mil \u20ac", "age": "27", "date_of_birth": "18/12/1992", "nation": "Gr\u00e9cia", "contract_expires": "30/06/2021"}, {"name": "Christos Mandas", "position": "Goleiro", "number": "35", "market_value": "350 mil \u20ac", "age": "19", "date_of_birth": "17/09/2001", "nation": "Gr\u00e9cia", "contract_expires": "30/06/2022"}, {"name": "Christos Theodorakis", "position": "Goleiro", "number": "13", "market_value": "250 mil \u20ac", "age": "24", "date_of_birth": "17/09/1996", "nation": "Gr\u00e9cia", "contract_expires": "30/06/2022"}, {"name": "Lucas Galv\u00e3o", "position": "Zagueiro", "number": "3", "market_value": "950 mil \u20ac", "age": "29", "date_of_birth": "22/06/1991", "nation": "Brasil", "contract_expires": "30/06/2021"}, {"name": "Spyros Risvanis", "position": "Zagueiro", "number": "44", "market_value": "700 mil \u20ac", "age": "26", "date_of_birth": "03/01/1994", "nation": "Gr\u00e9cia", "contract_expires": "30/06/2021"}, {"name": "Dimitrios Goutas", "position": "Zagueiro", "number": "4", "market_value": "500 mil \u20ac", "age": "26", "date_of_birth": "04/04/1994", "nation": "Gr\u00e9cia", "contract_expires": "30/06/2021"}, {"name": "Stefanos Stroungis", "position": "Zagueiro", "number": "29", "market_value": "200 mil \u20ac", "age": "22", "date_of_birth": "09/10/1997", "nation": "Gr\u00e9cia", "contract_expires": "30/06/2021"}, {"name": "Josip Tomasevic", "position": "Lateral Esq.", "number": "50", "market_value": "475 mil \u20ac", "age": "26", "date_of_birth": "04/03/1994", "nation": "Cro\u00e1cia", "contract_expires": "30/06/2022"}, {"name": "Kyriakos Kivrakidis", "position": "Lateral Dir.", "number": "19", "market_value": "400 mil \u20ac", "age": "28", "date_of_birth": "21/07/1992", "nation": "Gr\u00e9cia", "contract_expires": "30/06/2023"}, {"name": "Spyros Natsos", "position": "Lateral Dir.", "number": "16", "market_value": "300 mil \u20ac", "age": "22", "date_of_birth": "09/06/1998", "nation": "Gr\u00e9cia", "contract_expires": "30/06/2022"}, {"name": "Rodrigo Galo", "position": "Lateral Dir.", "number": "12", "market_value": "250 mil \u20ac", "age": "34", "date_of_birth": "19/09/1986", "nation": "Brasil", "contract_expires": "30/06/2021"}, {"name": "Azer Busuladzic", "position": "Volante", "number": "7", "market_value": "700 mil \u20ac", "age": "28", "date_of_birth": "12/11/1991", "nation": "B\u00f3snia-Herzegovina", "contract_expires": "30/06/2021"}, {"name": "Charilaos Charisis", "position": "Meia central", "number": "6", "market_value": "700 mil \u20ac", "age": "25", "date_of_birth": "12/01/1995", "nation": "Gr\u00e9cia", "contract_expires": "30/06/2021"}, {"name": "Patrick Salomon", "position": "Meia central", "number": "21", "market_value": "325 mil \u20ac", "age": "32", "date_of_birth": "10/06/1988", "nation": "\u00c1ustria", "contract_expires": "30/06/2022"}, {"name": "Giannis Ikonomidis", "position": "Meia central", "number": "18", "market_value": "300 mil \u20ac", "age": "22", "date_of_birth": "03/01/1998", "nation": "Gr\u00e9cia", "contract_expires": "30/06/2023"}, {"name": "Javier Umbides", "position": "Meia central", "number": "8", "market_value": "100 mil \u20ac", "age": "38", "date_of_birth": "09/02/1982", "nation": "Argentina", "contract_expires": "30/06/2021"}, {"name": "Bryan Rabello", "position": "Meia Ofensivo", "number": "10", "market_value": "600 mil \u20ac", "age": "26", "date_of_birth": "16/05/1994", "nation": "Chile", "contract_expires": "30/06/2021"}, {"name": "Juan Mu\u00f1iz", "position": "Meia Ofensivo", "number": "14", "market_value": "450 mil \u20ac", "age": "28", "date_of_birth": "14/03/1992", "nation": "Espanha", "contract_expires": "30/06/2023"}, {"name": "Clarck N'Sikulu", "position": "Ponta esquerda", "number": "59", "market_value": "700 mil \u20ac", "age": "28", "date_of_birth": "10/07/1992", "nation": "RD do Congo", "contract_expires": "30/06/2021"}, {"name": "Amir Agayev", "position": "Ponta esquerda", "number": "11", "market_value": "400 mil \u20ac", "age": "28", "date_of_birth": "10/02/1992", "nation": "Azerbaij\u00e3o", "contract_expires": "30/06/2021"}, {"name": "Georgios Manousos", "position": "Ponta Direita", "number": "9", "market_value": "400 mil \u20ac", "age": "32", "date_of_birth": "03/12/1987", "nation": "Gr\u00e9cia", "contract_expires": "30/06/2021"}, {"name": "Georgios Daviotis", "position": "Ponta Direita", "number": "27", "market_value": "200 mil \u20ac", "age": "22", "date_of_birth": "29/06/1998", "nation": "Gr\u00e9cia", "contract_expires": "30/06/2021"}, {"name": "Petros Giakoumakis", "position": "Atacante", "number": "20", "market_value": "350 mil \u20ac", "age": "28", "date_of_birth": "03/07/1992", "nation": "Gr\u00e9cia", "contract_expires": "30/06/2021"}, {"name": "Konstantinos Kotsopoulos", "position": "Centroavante", "number": "23", "market_value": "300 mil \u20ac", "age": "23", "date_of_birth": "17/02/1997", "nation": "Gr\u00e9cia", "contract_expires": "30/06/2021"}, {"name": "Antonis Trimmatis", "position": "Centroavante", "number": "17", "market_value": "200 mil \u20ac", "age": "21", "date_of_birth": "29/04/1999", "nation": "Gr\u00e9cia", "contract_expires": "30/06/2023"}]}, {"name": "PanetolikosGFS", "amount_of_players": "30", "media_age": "24,3", "market_value": "7,55 milh\u00f5es \u20ac", "manager": {"name": "Makis Chavos", "nation": "Gr\u00e9cia", "age": "51", "contract_expires": "-", "since": "15/10/2019"}, "players": [{"name": "Christopher Knett", "position": "Goleiro", "number": "1", "market_value": "350 mil \u20ac", "age": "30", "date_of_birth": "01/08/1990", "nation": "\u00c1ustria", "contract_expires": "30/06/2021"}, {"name": "Nikolaos Melissas", "position": "Goleiro", "number": "22", "market_value": "300 mil \u20ac", "age": "27", "date_of_birth": "24/02/1993", "nation": "Gr\u00e9cia", "contract_expires": "30/06/2022"}, {"name": "Christos Kalantzis", "position": "Goleiro", "number": "84", "market_value": "-\u00a0\u20ac", "age": "20", "date_of_birth": "19/06/2000", "nation": "Gr\u00e9cia", "contract_expires": "-"}, {"name": "Vangelis Kontogiannis", "position": "Goleiro", "number": "99", "market_value": "-\u00a0\u20ac", "age": "18", "date_of_birth": "09/01/2002", "nation": "Gr\u00e9cia", "contract_expires": "-"}, {"name": "Gerasimos Bakadimas", "position": "Defensor", "number": "-", "market_value": "50 mil \u20ac", "age": "20", "date_of_birth": "06/06/2000", "nation": "Gr\u00e9cia", "contract_expires": "30/06/2023"}, {"name": "Vasilios Skiadas", "position": "Defensor", "number": "25", "market_value": "-\u00a0\u20ac", "age": "18", "date_of_birth": "25/06/2002", "nation": "Gr\u00e9cia", "contract_expires": "-"}, {"name": "Aristotelis Karasalidis", "position": "Zagueiro", "number": "4", "market_value": "400 mil \u20ac", "age": "29", "date_of_birth": "03/05/1991", "nation": "Gr\u00e9cia", "contract_expires": "30/06/2022"}, {"name": "Alexandros Malis", "position": "Zagueiro", "number": "47", "market_value": "350 mil \u20ac", "age": "23", "date_of_birth": "19/03/1997", "nation": "Gr\u00e9cia", "contract_expires": "30/06/2023"}, {"name": "Apostolos Konstantopoulos", "position": "Zagueiro", "number": "66", "market_value": "150 mil \u20ac", "age": "18", "date_of_birth": "02/08/2002", "nation": "Gr\u00e9cia", "contract_expires": "30/06/2024"}, {"name": "El\u00edas Pereyra", "position": "Lateral Esq.", "number": "21", "market_value": "725 mil \u20ac", "age": "21", "date_of_birth": "15/02/1999", "nation": "Argentina", "contract_expires": "30/06/2023"}, {"name": "Alexandros Parras", "position": "Lateral Esq.", "number": "28", "market_value": "150 mil \u20ac", "age": "22", "date_of_birth": "12/05/1998", "nation": "Gr\u00e9cia", "contract_expires": "30/06/2021"}, {"name": "Vanderson", "position": "Lateral Esq.", "number": "3", "market_value": "100 mil \u20ac", "age": "35", "date_of_birth": "27/09/1984", "nation": "Brasil", "contract_expires": "30/06/2021"}, {"name": "Georgios Liavas", "position": "Lateral Dir.", "number": "54", "market_value": "450 mil \u20ac", "age": "19", "date_of_birth": "12/02/2001", "nation": "Gr\u00e9cia", "contract_expires": "30/06/2023"}, {"name": "Manolis Tzanakakis", "position": "Lateral Dir.", "number": "27", "market_value": "400 mil \u20ac", "age": "28", "date_of_birth": "30/04/1992", "nation": "Gr\u00e9cia", "contract_expires": "30/06/2021"}, {"name": "Paolo Medina", "position": "Lateral Dir.", "number": "2", "market_value": "300 mil \u20ac", "age": "21", "date_of_birth": "28/05/1999", "nation": "M\u00e9xico", "contract_expires": "30/06/2023"}, {"name": "Joaqu\u00edn Arzura", "position": "Volante", "number": "5", "market_value": "350 mil \u20ac", "age": "27", "date_of_birth": "18/05/1993", "nation": "Argentina", "contract_expires": "30/06/2021"}, {"name": "Angelos Tsingaras", "position": "Volante", "number": "37", "market_value": "350 mil \u20ac", "age": "21", "date_of_birth": "24/07/1999", "nation": "Gr\u00e9cia", "contract_expires": "30/06/2023"}, {"name": "Aymen Tahar", "position": "Meia central", "number": "6", "market_value": "250 mil \u20ac", "age": "30", "date_of_birth": "02/10/1989", "nation": "Arg\u00e9lia", "contract_expires": "30/06/2021"}, {"name": "Franco Mazurek", "position": "Meia Ofensivo", "number": "7", "market_value": "600 mil \u20ac", "age": "27", "date_of_birth": "24/09/1993", "nation": "Argentina", "contract_expires": "30/06/2021"}, {"name": "D\u00e1lcio", "position": "Meia Ofensivo", "number": "10", "market_value": "400 mil \u20ac", "age": "24", "date_of_birth": "22/05/1996", "nation": "Portugal", "contract_expires": "30/06/2021"}, {"name": "Christos Belevonis", "position": "Meia Ofensivo", "number": "80", "market_value": "-\u00a0\u20ac", "age": "18", "date_of_birth": "29/07/2002", "nation": "Gr\u00e9cia", "contract_expires": "30/06/2024"}, {"name": "Alexandros Kavvadias", "position": "Atacante", "number": "19", "market_value": "50 mil \u20ac", "age": "20", "date_of_birth": "10/05/2000", "nation": "Gr\u00e9cia", "contract_expires": "30/06/2023"}, {"name": "Spyros Skondras", "position": "Atacante", "number": "77", "market_value": "-\u00a0\u20ac", "age": "19", "date_of_birth": "06/04/2001", "nation": "Gr\u00e9cia", "contract_expires": "-"}, {"name": "Javier Mendoza", "position": "Ponta esquerda", "number": "30", "market_value": "300 mil \u20ac", "age": "28", "date_of_birth": "02/09/1992", "nation": "Argentina", "contract_expires": "30/06/2022"}, {"name": "Frederico Duarte", "position": "Ponta esquerda", "number": "14", "market_value": "250 mil \u20ac", "age": "21", "date_of_birth": "30/03/1999", "nation": "Portugal", "contract_expires": "30/06/2022"}, {"name": "Juan \u00c1lvarez", "position": "Ponta esquerda", "number": "15", "market_value": "250 mil \u20ac", "age": "22", "date_of_birth": "27/10/1997", "nation": "Argentina", "contract_expires": "30/06/2021"}, {"name": "Jorge D\u00edaz", "position": "Ponta Direita", "number": "11", "market_value": "300 mil \u20ac", "age": "31", "date_of_birth": "28/06/1989", "nation": "Uruguai", "contract_expires": "30/06/2021"}, {"name": "Gboly Ariyibi", "position": "Ponta Direita", "number": "12", "market_value": "300 mil \u20ac", "age": "25", "date_of_birth": "18/01/1995", "nation": "Estados Unidos da Am\u00e9rica", "contract_expires": "30/06/2021"}, {"name": "Nicol\u00e1s Mazzola", "position": "Centroavante", "number": "9", "market_value": "325 mil \u20ac", "age": "30", "date_of_birth": "28/01/1990", "nation": "Argentina", "contract_expires": "30/06/2021"}, {"name": "Nikolaos Vergos", "position": "Centroavante", "number": "29", "market_value": "100 mil \u20ac", "age": "24", "date_of_birth": "13/01/1996", "nation": "Gr\u00e9cia", "contract_expires": "30/06/2022"}]}, {"name": "PASGiannina", "amount_of_players": "26", "media_age": "24,9", "market_value": "5,53 milh\u00f5es \u20ac", "manager": {"name": "Argirios Giannikis", "nation": "Gr\u00e9cia", "age": "40", "contract_expires": "-", "since": "01/07/2019"}, "players": [{"name": "Makis Giannikoglou", "position": "Goleiro", "number": "1", "market_value": "300 mil \u20ac", "age": "27", "date_of_birth": "25/03/1993", "nation": "Gr\u00e9cia", "contract_expires": "30/06/2021"}, {"name": "Lefteris Choutesiotis", "position": "Goleiro", "number": "33", "market_value": "300 mil \u20ac", "age": "26", "date_of_birth": "20/07/1994", "nation": "Gr\u00e9cia", "contract_expires": "30/06/2021"}, {"name": "Giannis Kargas", "position": "Zagueiro", "number": "6", "market_value": "475 mil \u20ac", "age": "25", "date_of_birth": "09/12/1994", "nation": "Gr\u00e9cia", "contract_expires": "-"}, {"name": "Rodrigo Erramuspe", "position": "Zagueiro", "number": "-", "market_value": "200 mil \u20ac", "age": "30", "date_of_birth": "03/05/1990", "nation": "Argentina", "contract_expires": "-"}, {"name": "Epaminondas Pantelakis", "position": "Zagueiro", "number": "4", "market_value": "200 mil \u20ac", "age": "25", "date_of_birth": "10/02/1995", "nation": "Gr\u00e9cia", "contract_expires": "30/06/2021"}, {"name": "Pantelis Panourgias", "position": "Zagueiro", "number": "25", "market_value": "25 mil \u20ac", "age": "22", "date_of_birth": "13/04/1998", "nation": "Gr\u00e9cia", "contract_expires": "30/06/2021"}, {"name": "Georgios Gogos", "position": "Zagueiro", "number": "5", "market_value": "-\u00a0\u20ac", "age": "19", "date_of_birth": "11/07/2001", "nation": "Gr\u00e9cia", "contract_expires": "30/06/2022"}, {"name": "Marvin Peersman", "position": "Lateral Esq.", "number": "43", "market_value": "300 mil \u20ac", "age": "29", "date_of_birth": "10/02/1991", "nation": "B\u00e9lgica", "contract_expires": "30/06/2021"}, {"name": "Alexandros Kartalis", "position": "Lateral Esq.", "number": "7", "market_value": "175 mil \u20ac", "age": "25", "date_of_birth": "29/01/1995", "nation": "Gr\u00e9cia", "contract_expires": "30/06/2021"}, {"name": "Stavros Pilios", "position": "Lateral Esq.", "number": "23", "market_value": "50 mil \u20ac", "age": "19", "date_of_birth": "10/12/2000", "nation": "Gr\u00e9cia", "contract_expires": "30/06/2022"}, {"name": "Manolis Saliakas", "position": "Lateral Dir.", "number": "2", "market_value": "300 mil \u20ac", "age": "24", "date_of_birth": "12/09/1996", "nation": "Gr\u00e9cia", "contract_expires": "30/06/2022"}, {"name": "Antonis Ikonomopoulos", "position": "Lateral Dir.", "number": "24", "market_value": "50 mil \u20ac", "age": "22", "date_of_birth": "09/05/1998", "nation": "Gr\u00e9cia", "contract_expires": "30/06/2021"}, {"name": "Pavlos Grosdanis", "position": "Meio-Campo", "number": "47", "market_value": "-\u00a0\u20ac", "age": "18", "date_of_birth": "03/04/2002", "nation": "Gr\u00e9cia", "contract_expires": "-"}, {"name": "Juan Dom\u00ednguez", "position": "Volante", "number": "10", "market_value": "800 mil \u20ac", "age": "30", "date_of_birth": "08/01/1990", "nation": "Espanha", "contract_expires": "30/06/2021"}, {"name": "Fabry Castro", "position": "Volante", "number": "21", "market_value": "325 mil \u20ac", "age": "28", "date_of_birth": "21/02/1992", "nation": "Col\u00f4mbia", "contract_expires": "30/06/2021"}, {"name": "Stefanos Siontis", "position": "Volante", "number": "22", "market_value": "250 mil \u20ac", "age": "33", "date_of_birth": "04/09/1987", "nation": "Gr\u00e9cia", "contract_expires": "30/06/2021"}, {"name": "Angelos Liasos", "position": "Volante", "number": "80", "market_value": "-\u00a0\u20ac", "age": "20", "date_of_birth": "25/05/2000", "nation": "Gr\u00e9cia", "contract_expires": "30/06/2022"}, {"name": "Vladyslav Naumets", "position": "Meia Esquerda", "number": "17", "market_value": "50 mil \u20ac", "age": "21", "date_of_birth": "07/03/1999", "nation": "Ucr\u00e2nia", "contract_expires": "30/06/2022"}, {"name": "Christos Eleftheriadis", "position": "Ponta esquerda", "number": "9", "market_value": "300 mil \u20ac", "age": "28", "date_of_birth": "30/09/1991", "nation": "Gr\u00e9cia", "contract_expires": "30/06/2021"}, {"name": "Georgios Doumtsis", "position": "Ponta esquerda", "number": "-", "market_value": "-\u00a0\u20ac", "age": "20", "date_of_birth": "04/03/2000", "nation": "Gr\u00e9cia", "contract_expires": "-"}, {"name": "Alexandros Lolis", "position": "Ponta esquerda", "number": "19", "market_value": "-\u00a0\u20ac", "age": "18", "date_of_birth": "05/09/2002", "nation": "Gr\u00e9cia", "contract_expires": "-"}, {"name": "Fabricio Brener", "position": "Ponta Direita", "number": "-", "market_value": "275 mil \u20ac", "age": "22", "date_of_birth": "26/05/1998", "nation": "Argentina", "contract_expires": "30/06/2021"}, {"name": "Georgios Xydas", "position": "Ponta Direita", "number": "-", "market_value": "250 mil \u20ac", "age": "23", "date_of_birth": "14/04/1997", "nation": "Gr\u00e9cia", "contract_expires": "30/06/2021"}, {"name": "Georgios Pamlidis", "position": "Ponta Direita", "number": "14", "market_value": "250 mil \u20ac", "age": "26", "date_of_birth": "13/11/1993", "nation": "Gr\u00e9cia", "contract_expires": "30/06/2021"}, {"name": "Sandi Krizman", "position": "Centroavante", "number": "12", "market_value": "400 mil \u20ac", "age": "31", "date_of_birth": "17/08/1989", "nation": "Cro\u00e1cia", "contract_expires": "30/06/2021"}, {"name": "Jean-Baptiste L\u00e9o", "position": "Centroavante", "number": "29", "market_value": "250 mil \u20ac", "age": "24", "date_of_birth": "03/05/1996", "nation": "Fran\u00e7a", "contract_expires": "30/06/2021"}]}, {"name": "ArisThessaloniki", "amount_of_players": "25", "media_age": "26,8", "market_value": "11,43 milh\u00f5es \u20ac", "manager": {"name": "Apostolos Mantzios", "nation": "Gr\u00e9cia", "age": "50", "contract_expires": "30/06/2021", "since": "21/09/2020"}, "players": [{"name": "Juli\u00e1n Cuesta", "position": "Goleiro", "number": "23", "market_value": "450 mil \u20ac", "age": "29", "date_of_birth": "28/03/1991", "nation": "Espanha", "contract_expires": "30/06/2022"}, {"name": "Zacharie Boucher", "position": "Goleiro", "number": "30", "market_value": "400 mil \u20ac", "age": "28", "date_of_birth": "07/03/1992", "nation": "Fran\u00e7a", "contract_expires": "30/06/2022"}, {"name": "Fabian Ehmann", "position": "Goleiro", "number": "1", "market_value": "350 mil \u20ac", "age": "22", "date_of_birth": "28/08/1998", "nation": "\u00c1ustria", "contract_expires": "30/06/2021"}, {"name": "Lindsay Rose", "position": "Zagueiro", "number": "92", "market_value": "700 mil \u20ac", "age": "28", "date_of_birth": "08/02/1992", "nation": "Maur\u00edcias", "contract_expires": "30/06/2022"}, {"name": "Toni Datkovic", "position": "Zagueiro", "number": "4", "market_value": "550 mil \u20ac", "age": "26", "date_of_birth": "06/11/1993", "nation": "Cro\u00e1cia", "contract_expires": "30/06/2023"}, {"name": "Georgios Delizisis", "position": "Zagueiro", "number": "5", "market_value": "300 mil \u20ac", "age": "32", "date_of_birth": "01/12/1987", "nation": "Gr\u00e9cia", "contract_expires": "30/06/2021"}, {"name": "Petros Bagalianis", "position": "Zagueiro", "number": "40", "market_value": "200 mil \u20ac", "age": "19", "date_of_birth": "06/02/2001", "nation": "Gr\u00e9cia", "contract_expires": "30/06/2022"}, {"name": "Cristian Ganea", "position": "Lateral Esq.", "number": "22", "market_value": "800 mil \u20ac", "age": "28", "date_of_birth": "24/05/1992", "nation": "Rom\u00e9nia", "contract_expires": "30/06/2022"}, {"name": "Panagiotis Tsagalidis", "position": "Lateral Esq.", "number": "31", "market_value": "50 mil \u20ac", "age": "19", "date_of_birth": "05/03/2001", "nation": "Gr\u00e9cia", "contract_expires": "30/06/2022"}, {"name": "Panagiotis Sengergis", "position": "Lateral Esq.", "number": "27", "market_value": "-\u00a0\u20ac", "age": "19", "date_of_birth": "23/06/2001", "nation": "Gr\u00e9cia", "contract_expires": "-"}, {"name": "Daniel Sundgren", "position": "Lateral Dir.", "number": "21", "market_value": "500 mil \u20ac", "age": "29", "date_of_birth": "22/11/1990", "nation": "Su\u00e9cia", "contract_expires": "30/06/2022"}, {"name": "Emanuel Sakic", "position": "Lateral Dir.", "number": "66", "market_value": "400 mil \u20ac", "age": "29", "date_of_birth": "25/01/1991", "nation": "\u00c1ustria", "contract_expires": "30/06/2022"}, {"name": "Lucas Sasha", "position": "Volante", "number": "88", "market_value": "900 mil \u20ac", "age": "30", "date_of_birth": "01/03/1990", "nation": "Brasil", "contract_expires": "30/06/2021"}, {"name": "James Jeggo", "position": "Volante", "number": "6", "market_value": "650 mil \u20ac", "age": "28", "date_of_birth": "12/02/1992", "nation": "Austr\u00e1lia", "contract_expires": "30/06/2022"}, {"name": "Ali Adem", "position": "Volante", "number": "34", "market_value": "150 mil \u20ac", "age": "20", "date_of_birth": "01/06/2000", "nation": "Maced\u00f3nia do Norte", "contract_expires": "30/06/2024"}, {"name": "Javier Matilla", "position": "Meia central", "number": "26", "market_value": "400 mil \u20ac", "age": "32", "date_of_birth": "16/08/1988", "nation": "Espanha", "contract_expires": "30/06/2022"}, {"name": "Lerin Duarte", "position": "Meia central", "number": "8", "market_value": "200 mil \u20ac", "age": "30", "date_of_birth": "11/08/1990", "nation": "Holanda", "contract_expires": "30/06/2022"}, {"name": "Petros Bakoutsis", "position": "Meia central", "number": "38", "market_value": "100 mil \u20ac", "age": "19", "date_of_birth": "29/06/2001", "nation": "Gr\u00e9cia", "contract_expires": "30/06/2021"}, {"name": "Bruno Gama", "position": "Ponta esquerda", "number": "16", "market_value": "500 mil \u20ac", "age": "32", "date_of_birth": "15/11/1987", "nation": "Portugal", "contract_expires": "30/06/2022"}, {"name": "Facundo Bertoglio", "position": "Ponta esquerda", "number": "18", "market_value": "325 mil \u20ac", "age": "30", "date_of_birth": "30/06/1990", "nation": "Argentina", "contract_expires": "30/06/2022"}, {"name": "Giannis Fetfatzidis", "position": "Ponta Direita", "number": "10", "market_value": "1,50 milh\u00f5es \u20ac", "age": "29", "date_of_birth": "21/12/1990", "nation": "Gr\u00e9cia", "contract_expires": "30/06/2021"}, {"name": "Daniel Mancini", "position": "Ponta Direita", "number": "7", "market_value": "700 mil \u20ac", "age": "23", "date_of_birth": "11/11/1996", "nation": "Argentina", "contract_expires": "30/06/2022"}, {"name": "Konstantinos Chatzipirpiridis", "position": "Ponta Direita", "number": "33", "market_value": "-\u00a0\u20ac", "age": "19", "date_of_birth": "01/05/2001", "nation": "Gr\u00e9cia", "contract_expires": "30/06/2023"}, {"name": "Cristian L\u00f3pez", "position": "Centroavante", "number": "11", "market_value": "800 mil \u20ac", "age": "31", "date_of_birth": "27/04/1989", "nation": "Espanha", "contract_expires": "30/06/2022"}, {"name": "Dimitrios Manos", "position": "Centroavante", "number": "9", "market_value": "500 mil \u20ac", "age": "26", "date_of_birth": "16/09/1994", "nation": "Gr\u00e9cia", "contract_expires": "30/06/2022"}]}, {"name": "PASLamia1964", "amount_of_players": "29", "media_age": "26,8", "market_value": "6,55 milh\u00f5es \u20ac", "manager": {"name": "Georgios Petrakis", "nation": "Gr\u00e9cia", "age": "32", "contract_expires": "30/06/2021", "since": "25/06/2020"}, "players": [{"name": "Konstantinos Theodoropoulos", "position": "Goleiro", "number": "31", "market_value": "300 mil \u20ac", "age": "30", "date_of_birth": "27/03/1990", "nation": "Gr\u00e9cia", "contract_expires": "30/06/2021"}, {"name": "Devis Epassy", "position": "Goleiro", "number": "1", "market_value": "250 mil \u20ac", "age": "27", "date_of_birth": "02/02/1993", "nation": "Fran\u00e7a", "contract_expires": "30/06/2021"}, {"name": "Panagiotis Katsikas", "position": "Goleiro", "number": "99", "market_value": "150 mil \u20ac", "age": "21", "date_of_birth": "10/03/1999", "nation": "Gr\u00e9cia", "contract_expires": "30/06/2022"}, {"name": "Daniel Adejo", "position": "Zagueiro", "number": "4", "market_value": "300 mil \u20ac", "age": "31", "date_of_birth": "07/08/1989", "nation": "Nig\u00e9ria", "contract_expires": "30/06/2021"}, {"name": "Adam Tzanetopoulos", "position": "Zagueiro", "number": "5", "market_value": "250 mil \u20ac", "age": "25", "date_of_birth": "10/02/1995", "nation": "Gr\u00e9cia", "contract_expires": "30/06/2021"}, {"name": "Angelos Zioulis", "position": "Zagueiro", "number": "20", "market_value": "250 mil \u20ac", "age": "25", "date_of_birth": "01/02/1995", "nation": "Gr\u00e9cia", "contract_expires": "30/06/2021"}, {"name": "Patrick Bahanack", "position": "Zagueiro", "number": "29", "market_value": "150 mil \u20ac", "age": "23", "date_of_birth": "03/08/1997", "nation": "Camar\u00f5es", "contract_expires": "30/06/2021"}, {"name": "Loukas Vyntra", "position": "Zagueiro", "number": "24", "market_value": "100 mil \u20ac", "age": "39", "date_of_birth": "05/02/1981", "nation": "Gr\u00e9cia", "contract_expires": "30/06/2021"}, {"name": "Georgios Saramantas", "position": "Lateral Esq.", "number": "3", "market_value": "300 mil \u20ac", "age": "28", "date_of_birth": "29/01/1992", "nation": "Gr\u00e9cia", "contract_expires": "30/06/2021"}, {"name": "Giannis Skondras", "position": "Lateral Dir.", "number": "23", "market_value": "300 mil \u20ac", "age": "30", "date_of_birth": "21/02/1990", "nation": "Gr\u00e9cia", "contract_expires": "30/06/2021"}, {"name": "Konstantinos Provydakis", "position": "Lateral Dir.", "number": "2", "market_value": "150 mil \u20ac", "age": "24", "date_of_birth": "21/05/1996", "nation": "Gr\u00e9cia", "contract_expires": "30/06/2021"}, {"name": "Danny Bejarano", "position": "Volante", "number": "16", "market_value": "400 mil \u20ac", "age": "26", "date_of_birth": "03/01/1994", "nation": "Bol\u00edvia", "contract_expires": "30/06/2021"}, {"name": "Ibrahima Niasse", "position": "Volante", "number": "6", "market_value": "200 mil \u20ac", "age": "32", "date_of_birth": "18/04/1988", "nation": "Senegal", "contract_expires": "30/06/2021"}, {"name": "Konstantinos Bouloulis", "position": "Volante", "number": "61", "market_value": "200 mil \u20ac", "age": "26", "date_of_birth": "07/12/1993", "nation": "Gr\u00e9cia", "contract_expires": "30/06/2021"}, {"name": "Guga Palavandishvili", "position": "Volante", "number": "8", "market_value": "100 mil \u20ac", "age": "27", "date_of_birth": "14/08/1993", "nation": "Ge\u00f3rgia", "contract_expires": "30/06/2021"}, {"name": "Christoforos Karagiannis", "position": "Volante", "number": "90", "market_value": "50 mil \u20ac", "age": "20", "date_of_birth": "09/12/1999", "nation": "Gr\u00e9cia", "contract_expires": "30/06/2021"}, {"name": "Elini Dimoutsos", "position": "Meia central", "number": "21", "market_value": "300 mil \u20ac", "age": "32", "date_of_birth": "18/08/1988", "nation": "Gr\u00e9cia", "contract_expires": "30/06/2021"}, {"name": "Theodoros Vasilakakis", "position": "Meia Ofensivo", "number": "-", "market_value": "400 mil \u20ac", "age": "32", "date_of_birth": "20/07/1988", "nation": "Gr\u00e9cia", "contract_expires": "30/06/2021"}, {"name": "Konstantinos Nikolopoulos", "position": "Meia Ofensivo", "number": "22", "market_value": "50 mil \u20ac", "age": "18", "date_of_birth": "13/07/2002", "nation": "Gr\u00e9cia", "contract_expires": "30/06/2022"}, {"name": "Zisis Chatzistravos", "position": "Meia Ofensivo", "number": "28", "market_value": "-\u00a0\u20ac", "age": "20", "date_of_birth": "16/12/1999", "nation": "Gr\u00e9cia", "contract_expires": "30/06/2021"}, {"name": "Lazar Romanic", "position": "Ponta esquerda", "number": "18", "market_value": "450 mil \u20ac", "age": "22", "date_of_birth": "23/03/1998", "nation": "S\u00e9rvia", "contract_expires": "30/06/2021"}, {"name": "Leonardo Villalba", "position": "Ponta esquerda", "number": "10", "market_value": "300 mil \u20ac", "age": "25", "date_of_birth": "29/11/1994", "nation": "Argentina", "contract_expires": "30/06/2021"}, {"name": "Nikolaos Tsoukalos", "position": "Ponta esquerda", "number": "45", "market_value": "150 mil \u20ac", "age": "28", "date_of_birth": "23/03/1992", "nation": "Gr\u00e9cia", "contract_expires": "30/06/2021"}, {"name": "Vasilios Kostikas", "position": "Ponta esquerda", "number": "77", "market_value": "50 mil \u20ac", "age": "21", "date_of_birth": "04/09/1999", "nation": "Gr\u00e9cia", "contract_expires": "30/06/2021"}, {"name": "Andreas Vasilogiannis", "position": "Ponta Direita", "number": "7", "market_value": "300 mil \u20ac", "age": "29", "date_of_birth": "21/02/1991", "nation": "Gr\u00e9cia", "contract_expires": "30/06/2021"}, {"name": "Bachana Arabuli", "position": "Centroavante", "number": "-", "market_value": "450 mil \u20ac", "age": "26", "date_of_birth": "05/01/1994", "nation": "Ge\u00f3rgia", "contract_expires": "30/06/2021"}, {"name": "Miguel Bianconi", "position": "Centroavante", "number": "9", "market_value": "300 mil \u20ac", "age": "28", "date_of_birth": "14/05/1992", "nation": "Brasil", "contract_expires": "30/06/2021"}, {"name": "Anastasios Karamanos", "position": "Centroavante", "number": "11", "market_value": "300 mil \u20ac", "age": "30", "date_of_birth": "21/09/1990", "nation": "Gr\u00e9cia", "contract_expires": "30/06/2021"}, {"name": "Anestis Vlachomitros", "position": "Centroavante", "number": "17", "market_value": "50 mil \u20ac", "age": "18", "date_of_birth": "06/11/2001", "nation": "Gr\u00e9cia", "contract_expires": "30/06/2022"}]}, {"name": "OFICreta", "amount_of_players": "29", "media_age": "25,6", "market_value": "10,25 milh\u00f5es \u20ac", "manager": {"name": "Georgios Simos", "nation": "Gr\u00e9cia", "age": "42", "contract_expires": "30/06/2021", "since": "12/07/2019"}, "players": [{"name": "Dimitrios Sotiriou", "position": "Goleiro", "number": "32", "market_value": "300 mil \u20ac", "age": "33", "date_of_birth": "13/09/1987", "nation": "Gr\u00e9cia", "contract_expires": "30/06/2023"}, {"name": "Boy Waterman", "position": "Goleiro", "number": "24", "market_value": "250 mil \u20ac", "age": "36", "date_of_birth": "24/01/1984", "nation": "Holanda", "contract_expires": "30/06/2022"}, {"name": "Vasilios Sifakis", "position": "Goleiro", "number": "53", "market_value": "50 mil \u20ac", "age": "18", "date_of_birth": "27/10/2001", "nation": "Gr\u00e9cia", "contract_expires": "30/06/2023"}, {"name": "Vahid Selimovic", "position": "Zagueiro", "number": "5", "market_value": "650 mil \u20ac", "age": "23", "date_of_birth": "03/04/1997", "nation": "Luxemburgo", "contract_expires": "30/06/2023"}, {"name": "Praxitelis Vouros", "position": "Zagueiro", "number": "14", "market_value": "650 mil \u20ac", "age": "25", "date_of_birth": "05/05/1995", "nation": "Gr\u00e9cia", "contract_expires": "30/06/2023"}, {"name": "Nikolaos Vafeas", "position": "Zagueiro", "number": "13", "market_value": "300 mil \u20ac", "age": "23", "date_of_birth": "21/02/1997", "nation": "Gr\u00e9cia", "contract_expires": "30/06/2022"}, {"name": "Konstantinos Giannoulis", "position": "Zagueiro", "number": "18", "market_value": "300 mil \u20ac", "age": "32", "date_of_birth": "09/12/1987", "nation": "Gr\u00e9cia", "contract_expires": "30/06/2022"}, {"name": "Apostolos Diamantis", "position": "Zagueiro", "number": "15", "market_value": "250 mil \u20ac", "age": "20", "date_of_birth": "20/05/2000", "nation": "Gr\u00e9cia", "contract_expires": "30/06/2024"}, {"name": "Nikolaos Korovesis", "position": "Lateral Esq.", "number": "34", "market_value": "450 mil \u20ac", "age": "29", "date_of_birth": "10/08/1991", "nation": "Gr\u00e9cia", "contract_expires": "30/06/2022"}, {"name": "Odysseas Lymperakis", "position": "Lateral Esq.", "number": "3", "market_value": "250 mil \u20ac", "age": "22", "date_of_birth": "05/06/1998", "nation": "Gr\u00e9cia", "contract_expires": "30/06/2024"}, {"name": "Nikolaos Marinakis", "position": "Lateral Dir.", "number": "6", "market_value": "450 mil \u20ac", "age": "27", "date_of_birth": "12/09/1993", "nation": "Gr\u00e9cia", "contract_expires": "30/06/2023"}, {"name": "Abdul Rahman Weiss", "position": "Lateral Dir.", "number": "2", "market_value": "325 mil \u20ac", "age": "22", "date_of_birth": "14/06/1998", "nation": "Gr\u00e9cia", "contract_expires": "30/06/2024"}, {"name": "Miguel Mellado", "position": "Volante", "number": "29", "market_value": "450 mil \u20ac", "age": "27", "date_of_birth": "18/03/1993", "nation": "Argentina", "contract_expires": "30/06/2024"}, {"name": "Vajebah Sakor", "position": "Volante", "number": "4", "market_value": "350 mil \u20ac", "age": "24", "date_of_birth": "24/04/1996", "nation": "Noruega", "contract_expires": "30/06/2021"}, {"name": "Paschalis Staikos", "position": "Volante", "number": "26", "market_value": "300 mil \u20ac", "age": "24", "date_of_birth": "08/02/1996", "nation": "Gr\u00e9cia", "contract_expires": "30/06/2023"}, {"name": "Theodoros Mingos", "position": "Meia central", "number": "38", "market_value": "150 mil \u20ac", "age": "22", "date_of_birth": "06/02/1998", "nation": "Gr\u00e9cia", "contract_expires": "30/06/2022"}, {"name": "Georgios Sournakis", "position": "Meia central", "number": "49", "market_value": "100 mil \u20ac", "age": "20", "date_of_birth": "07/11/1999", "nation": "Gr\u00e9cia", "contract_expires": "30/06/2021"}, {"name": "Adil Nabi", "position": "Meia Ofensivo", "number": "10", "market_value": "500 mil \u20ac", "age": "26", "date_of_birth": "28/02/1994", "nation": "Inglaterra", "contract_expires": "30/06/2021"}, {"name": "Juan Neira", "position": "Meia Ofensivo", "number": "8", "market_value": "450 mil \u20ac", "age": "31", "date_of_birth": "21/02/1989", "nation": "Argentina", "contract_expires": "30/06/2021"}, {"name": "Frixos Grivas", "position": "Meia Ofensivo", "number": "28", "market_value": "100 mil \u20ac", "age": "20", "date_of_birth": "23/09/2000", "nation": "Gr\u00e9cia", "contract_expires": "30/06/2024"}, {"name": "Kosmas Tsilianidis", "position": "Ponta esquerda", "number": "19", "market_value": "700 mil \u20ac", "age": "26", "date_of_birth": "09/05/1994", "nation": "Gr\u00e9cia", "contract_expires": "30/06/2023"}, {"name": "Nazareno Sol\u00eds", "position": "Ponta esquerda", "number": "11", "market_value": "475 mil \u20ac", "age": "26", "date_of_birth": "22/04/1994", "nation": "Argentina", "contract_expires": "30/06/2021"}, {"name": "Felipe Souza Ferreyra", "position": "Ponta esquerda", "number": "9", "market_value": "450 mil \u20ac", "age": "22", "date_of_birth": "21/05/1998", "nation": "Brasil", "contract_expires": "30/06/2023"}, {"name": "F\u00e1bio Sturgeon", "position": "Ponta Direita", "number": "7", "market_value": "600 mil \u20ac", "age": "26", "date_of_birth": "04/02/1994", "nation": "Portugal", "contract_expires": "30/06/2023"}, {"name": "Ricardo Vaz", "position": "Ponta Direita", "number": "21", "market_value": "350 mil \u20ac", "age": "25", "date_of_birth": "26/11/1994", "nation": "Portugal", "contract_expires": "30/06/2021"}, {"name": "Adri\u00e1n Sardinero", "position": "Ponta Direita", "number": "22", "market_value": "325 mil \u20ac", "age": "29", "date_of_birth": "13/10/1990", "nation": "Espanha", "contract_expires": "30/06/2022"}, {"name": "Vangelis Nikokyrakis", "position": "Ponta Direita", "number": "17", "market_value": "100 mil \u20ac", "age": "18", "date_of_birth": "04/10/2001", "nation": "Gr\u00e9cia", "contract_expires": "30/06/2023"}, {"name": "Apostolos Giannou", "position": "Centroavante", "number": "-", "market_value": "475 mil \u20ac", "age": "30", "date_of_birth": "25/01/1990", "nation": "Austr\u00e1lia", "contract_expires": "30/06/2022"}, {"name": "Alexandros Gargalatzidis", "position": "Centroavante", "number": "23", "market_value": "150 mil \u20ac", "age": "20", "date_of_birth": "12/04/2000", "nation": "Gr\u00e9cia", "contract_expires": "30/06/2024"}]}, {"name": "AsterasTripolis", "amount_of_players": "35", "media_age": "24,4", "market_value": "9,23 milh\u00f5es \u20ac", "manager": {"name": "Milan Rastavac", "nation": "S\u00e9rvia", "age": "46", "contract_expires": "30/06/2021", "since": "05/12/2019"}, "players": [{"name": "Nikolaos Papadopoulos", "position": "Goleiro", "number": "1", "market_value": "350 mil \u20ac", "age": "30", "date_of_birth": "11/04/1990", "nation": "Gr\u00e9cia", "contract_expires": "30/06/2022"}, {"name": "Antonis Tsiftsis", "position": "Goleiro", "number": "99", "market_value": "150 mil \u20ac", "age": "21", "date_of_birth": "21/07/1999", "nation": "Gr\u00e9cia", "contract_expires": "30/06/2022"}, {"name": "Fotis Sgouris", "position": "Goleiro", "number": "33", "market_value": "-\u00a0\u20ac", "age": "18", "date_of_birth": "29/04/2002", "nation": "Gr\u00e9cia", "contract_expires": "30/06/2023"}, {"name": "Fotis Pseftis", "position": "Goleiro", "number": "91", "market_value": "-\u00a0\u20ac", "age": "17", "date_of_birth": "19/01/2003", "nation": "Gr\u00e9cia", "contract_expires": "-"}, {"name": "Triantafyllos Pasalidis", "position": "Zagueiro", "number": "4", "market_value": "600 mil \u20ac", "age": "24", "date_of_birth": "19/07/1996", "nation": "Gr\u00e9cia", "contract_expires": "30/06/2022"}, {"name": "Dani Su\u00e1rez", "position": "Zagueiro", "number": "15", "market_value": "450 mil \u20ac", "age": "30", "date_of_birth": "05/07/1990", "nation": "Espanha", "contract_expires": "30/06/2021"}, {"name": "Georgios Antzoulas", "position": "Zagueiro", "number": "42", "market_value": "450 mil \u20ac", "age": "20", "date_of_birth": "04/02/2000", "nation": "Gr\u00e9cia", "contract_expires": "-"}, {"name": "Pepe Casta\u00f1o", "position": "Zagueiro", "number": "19", "market_value": "100 mil \u20ac", "age": "21", "date_of_birth": "10/12/1998", "nation": "Espanha", "contract_expires": "30/06/2023"}, {"name": "Giannis Christopoulos", "position": "Zagueiro", "number": "45", "market_value": "100 mil \u20ac", "age": "20", "date_of_birth": "22/07/2000", "nation": "Gr\u00e9cia", "contract_expires": "30/06/2021"}, {"name": "Oluwatobiloba Alagbe", "position": "Zagueiro", "number": "69", "market_value": "50 mil \u20ac", "age": "20", "date_of_birth": "24/04/2000", "nation": "Nig\u00e9ria", "contract_expires": "-"}, {"name": "Christos Tasoulis", "position": "Lateral Esq.", "number": "3", "market_value": "350 mil \u20ac", "age": "29", "date_of_birth": "03/05/1991", "nation": "Gr\u00e9cia", "contract_expires": "30/06/2021"}, {"name": "Federico \u00c1lvarez", "position": "Lateral Esq.", "number": "29", "market_value": "325 mil \u20ac", "age": "26", "date_of_birth": "07/08/1994", "nation": "Argentina", "contract_expires": "30/06/2023"}, {"name": "Ilias Christopoulos", "position": "Lateral Esq.", "number": "39", "market_value": "-\u00a0\u20ac", "age": "17", "date_of_birth": "02/02/2003", "nation": "Gr\u00e9cia", "contract_expires": "-"}, {"name": "Giannis Kotsiras", "position": "Lateral Dir.", "number": "27", "market_value": "450 mil \u20ac", "age": "27", "date_of_birth": "16/12/1992", "nation": "Gr\u00e9cia", "contract_expires": "30/06/2022"}, {"name": "Rub\u00e9n Garc\u00eda", "position": "Lateral Dir.", "number": "2", "market_value": "200 mil \u20ac", "age": "21", "date_of_birth": "23/10/1998", "nation": "Espanha", "contract_expires": "30/06/2023"}, {"name": "Alexandros Kardaris", "position": "Lateral Dir.", "number": "43", "market_value": "50 mil \u20ac", "age": "19", "date_of_birth": "14/01/2001", "nation": "Gr\u00e9cia", "contract_expires": "-"}, {"name": "Jos\u00e9 Luis Valiente", "position": "Volante", "number": "6", "market_value": "400 mil \u20ac", "age": "29", "date_of_birth": "18/05/1991", "nation": "Espanha", "contract_expires": "30/06/2021"}, {"name": "Franco Bellocq", "position": "Volante", "number": "14", "market_value": "250 mil \u20ac", "age": "26", "date_of_birth": "15/10/1993", "nation": "Argentina", "contract_expires": "30/06/2021"}, {"name": "Matias Iglesias", "position": "Volante", "number": "17", "market_value": "100 mil \u20ac", "age": "35", "date_of_birth": "18/04/1985", "nation": "Argentina", "contract_expires": "30/06/2021"}, {"name": "Borja Fern\u00e1ndez", "position": "Meia central", "number": "8", "market_value": "400 mil \u20ac", "age": "25", "date_of_birth": "16/08/1995", "nation": "Espanha", "contract_expires": "30/06/2021"}, {"name": "Juan Munafo", "position": "Meia central", "number": "12", "market_value": "300 mil \u20ac", "age": "32", "date_of_birth": "20/03/1988", "nation": "Argentina", "contract_expires": "30/06/2021"}, {"name": "Georgios Kanellopoulos", "position": "Meia central", "number": "24", "market_value": "50 mil \u20ac", "age": "20", "date_of_birth": "29/01/2000", "nation": "Gr\u00e9cia", "contract_expires": "30/06/2021"}, {"name": "Athanasios Michopoulos", "position": "Meia central", "number": "92", "market_value": "-\u00a0\u20ac", "age": "18", "date_of_birth": "20/01/2002", "nation": "Gr\u00e9cia", "contract_expires": "-"}, {"name": "Eneko Capilla", "position": "Meia Ofensivo", "number": "5", "market_value": "450 mil \u20ac", "age": "25", "date_of_birth": "13/06/1995", "nation": "Espanha", "contract_expires": "30/06/2022"}, {"name": "Brian Orosco", "position": "Meia Ofensivo", "number": "18", "market_value": "400 mil \u20ac", "age": "22", "date_of_birth": "28/02/1998", "nation": "Argentina", "contract_expires": "30/06/2023"}, {"name": "Panagiotis Tzimas", "position": "Meia Ofensivo", "number": "21", "market_value": "150 mil \u20ac", "age": "19", "date_of_birth": "12/03/2001", "nation": "Gr\u00e9cia", "contract_expires": "30/06/2021"}, {"name": "Sito", "position": "Ponta esquerda", "number": "40", "market_value": "400 mil \u20ac", "age": "23", "date_of_birth": "18/11/1996", "nation": "Espanha", "contract_expires": "30/06/2022"}, {"name": "Rodrigo G\u00f3mez", "position": "Ponta Direita", "number": "20", "market_value": "800 mil \u20ac", "age": "27", "date_of_birth": "02/01/1993", "nation": "Argentina", "contract_expires": "30/06/2023"}, {"name": "Adri\u00e1n Riera", "position": "Ponta Direita", "number": "23", "market_value": "450 mil \u20ac", "age": "24", "date_of_birth": "19/04/1996", "nation": "Espanha", "contract_expires": "30/06/2021"}, {"name": "L\u00e9o Tilica", "position": "Ponta Direita", "number": "7", "market_value": "100 mil \u20ac", "age": "25", "date_of_birth": "20/04/1995", "nation": "Brasil", "contract_expires": "30/06/2023"}, {"name": "Luis Fern\u00e1ndez", "position": "Centroavante", "number": "10", "market_value": "700 mil \u20ac", "age": "27", "date_of_birth": "23/09/1993", "nation": "Espanha", "contract_expires": "30/06/2021"}, {"name": "Crespi", "position": "Centroavante", "number": "11", "market_value": "350 mil \u20ac", "age": "23", "date_of_birth": "30/09/1996", "nation": "Espanha", "contract_expires": "30/06/2022"}, {"name": "Jer\u00f3nimo Barrales", "position": "Centroavante", "number": "9", "market_value": "200 mil \u20ac", "age": "34", "date_of_birth": "28/01/1986", "nation": "Argentina", "contract_expires": "30/06/2021"}, {"name": "Sudais Ali Baba", "position": "Centroavante", "number": "97", "market_value": "100 mil \u20ac", "age": "20", "date_of_birth": "25/08/2000", "nation": "Nig\u00e9ria", "contract_expires": "-"}, {"name": "Alexandros Tereziou", "position": "Centroavante", "number": "31", "market_value": "-\u00a0\u20ac", "age": "20", "date_of_birth": "01/03/2000", "nation": "Gr\u00e9cia", "contract_expires": "-"}]}, {"name": "PAOKThessaloniki", "amount_of_players": "34", "media_age": "25,6", "market_value": "61,00 milh\u00f5es \u20ac", "manager": {"name": "Abel Ferreira", "nation": "Portugal", "age": "41", "contract_expires": "30/06/2022", "since": "01/07/2019"}, "players": [{"name": "Rodrigo Rey", "position": "Goleiro", "number": "1", "market_value": "1,20 milh\u00f5es \u20ac", "age": "29", "date_of_birth": "08/03/1991", "nation": "Argentina", "contract_expires": "30/06/2021"}, {"name": "Alexandros Paschalakis", "position": "Goleiro", "number": "31", "market_value": "1,20 milh\u00f5es \u20ac", "age": "31", "date_of_birth": "28/07/1989", "nation": "Gr\u00e9cia", "contract_expires": "30/06/2022"}, {"name": "Zivko Zivkovic", "position": "Goleiro", "number": "88", "market_value": "800 mil \u20ac", "age": "31", "date_of_birth": "14/04/1989", "nation": "S\u00e9rvia", "contract_expires": "30/06/2022"}, {"name": "Sverrir Ingi Ingason", "position": "Zagueiro", "number": "4", "market_value": "3,50 milh\u00f5es \u20ac", "age": "27", "date_of_birth": "05/08/1993", "nation": "Isl\u00e2ndia", "contract_expires": "30/06/2022"}, {"name": "Fernando Varela", "position": "Zagueiro", "number": "5", "market_value": "1,20 milh\u00f5es \u20ac", "age": "32", "date_of_birth": "26/11/1987", "nation": "Cabo Verde", "contract_expires": "30/06/2022"}, {"name": "Enea Mihaj", "position": "Zagueiro", "number": "6", "market_value": "900 mil \u20ac", "age": "22", "date_of_birth": "05/07/1998", "nation": "Alb\u00e2nia", "contract_expires": "30/06/2023"}, {"name": "Jos\u00e9 Crespo", "position": "Zagueiro", "number": "15", "market_value": "800 mil \u20ac", "age": "33", "date_of_birth": "09/02/1987", "nation": "Espanha", "contract_expires": "30/06/2021"}, {"name": "Giannis Michailidis", "position": "Zagueiro", "number": "49", "market_value": "400 mil \u20ac", "age": "20", "date_of_birth": "18/02/2000", "nation": "Gr\u00e9cia", "contract_expires": "30/06/2023"}, {"name": "Dimitrios Giannoulis", "position": "Lateral Esq.", "number": "23", "market_value": "4,50 milh\u00f5es \u20ac", "age": "24", "date_of_birth": "17/10/1995", "nation": "Gr\u00e9cia", "contract_expires": "30/06/2022"}, {"name": "Adrian Nilsen Pereira", "position": "Lateral Esq.", "number": "16", "market_value": "400 mil \u20ac", "age": "21", "date_of_birth": "31/08/1999", "nation": "Noruega", "contract_expires": "30/06/2024"}, {"name": "Moussa Wagu\u00e9", "position": "Lateral Dir.", "number": "18", "market_value": "6,70 milh\u00f5es \u20ac", "age": "21", "date_of_birth": "04/10/1998", "nation": "Senegal", "contract_expires": "30/06/2021"}, {"name": "Rodrigo", "position": "Lateral Dir.", "number": "2", "market_value": "1,50 milh\u00f5es \u20ac", "age": "27", "date_of_birth": "26/12/1992", "nation": "Brasil", "contract_expires": "30/06/2022"}, {"name": "L\u00e9o Matos", "position": "Lateral Dir.", "number": "3", "market_value": "600 mil \u20ac", "age": "34", "date_of_birth": "02/04/1986", "nation": "Brasil", "contract_expires": "30/06/2021"}, {"name": "Lefteris Lyratzis", "position": "Lateral Dir.", "number": "19", "market_value": "400 mil \u20ac", "age": "20", "date_of_birth": "22/02/2000", "nation": "Gr\u00e9cia", "contract_expires": "30/06/2022"}, {"name": "Anderson Esiti", "position": "Volante", "number": "24", "market_value": "2,80 milh\u00f5es \u20ac", "age": "26", "date_of_birth": "24/05/1994", "nation": "Nig\u00e9ria", "contract_expires": "30/06/2023"}, {"name": "Josip Misic", "position": "Meia central", "number": "27", "market_value": "3,00 milh\u00f5es \u20ac", "age": "26", "date_of_birth": "28/06/1994", "nation": "Cro\u00e1cia", "contract_expires": "30/06/2021"}, {"name": "Douglas Augusto", "position": "Meia central", "number": "33", "market_value": "3,00 milh\u00f5es \u20ac", "age": "23", "date_of_birth": "13/01/1997", "nation": "Brasil", "contract_expires": "30/06/2023"}, {"name": "Omar El Kaddouri", "position": "Meia central", "number": "7", "market_value": "1,50 milh\u00f5es \u20ac", "age": "30", "date_of_birth": "21/08/1990", "nation": "Marrocos", "contract_expires": "30/06/2021"}, {"name": "Stefan Schwab", "position": "Meia central", "number": "22", "market_value": "1,50 milh\u00f5es \u20ac", "age": "29", "date_of_birth": "27/09/1990", "nation": "\u00c1ustria", "contract_expires": "30/06/2022"}, {"name": "Nikoloz Ninua", "position": "Meia central", "number": "32", "market_value": "900 mil \u20ac", "age": "21", "date_of_birth": "22/06/1999", "nation": "Ge\u00f3rgia", "contract_expires": "30/06/2024"}, {"name": "Thibault Moulin", "position": "Meia central", "number": "-", "market_value": "500 mil \u20ac", "age": "30", "date_of_birth": "13/01/1990", "nation": "Fran\u00e7a", "contract_expires": "31/12/2020"}, {"name": "Konstantinos Balogiannis", "position": "Meia central", "number": "26", "market_value": "350 mil \u20ac", "age": "21", "date_of_birth": "08/02/1999", "nation": "Gr\u00e9cia", "contract_expires": "30/06/2021"}, {"name": "Theocharis Tsingaras", "position": "Meia central", "number": "51", "market_value": "200 mil \u20ac", "age": "20", "date_of_birth": "20/08/2000", "nation": "Gr\u00e9cia", "contract_expires": "30/06/2021"}, {"name": "Dimitrios Pelkas", "position": "Meia Ofensivo", "number": "10", "market_value": "2,50 milh\u00f5es \u20ac", "age": "26", "date_of_birth": "26/10/1993", "nation": "Gr\u00e9cia", "contract_expires": "30/06/2021"}, {"name": "Diego Biseswar", "position": "Meia Ofensivo", "number": "21", "market_value": "1,80 milh\u00f5es \u20ac", "age": "32", "date_of_birth": "08/03/1988", "nation": "Holanda", "contract_expires": "30/06/2022"}, {"name": "Georgios Vrakas", "position": "Meia Ofensivo", "number": "29", "market_value": "100 mil \u20ac", "age": "19", "date_of_birth": "28/04/2001", "nation": "Gr\u00e9cia", "contract_expires": "30/06/2023"}, {"name": "Amr Warda", "position": "Ponta esquerda", "number": "74", "market_value": "1,00 milh\u00f5es \u20ac", "age": "27", "date_of_birth": "17/09/1993", "nation": "Egito", "contract_expires": "30/06/2021"}, {"name": "Christos Tzolis", "position": "Ponta esquerda", "number": "11", "market_value": "400 mil \u20ac", "age": "18", "date_of_birth": "30/01/2002", "nation": "Gr\u00e9cia", "contract_expires": "30/06/2024"}, {"name": "L\u00e9o Jab\u00e1", "position": "Ponta Direita", "number": "98", "market_value": "5,00 milh\u00f5es \u20ac", "age": "22", "date_of_birth": "02/08/1998", "nation": "Brasil", "contract_expires": "30/06/2023"}, {"name": "Andrija Zivkovic", "position": "Ponta Direita", "number": "14", "market_value": "4,00 milh\u00f5es \u20ac", "age": "24", "date_of_birth": "11/07/1996", "nation": "S\u00e9rvia", "contract_expires": "30/06/2022"}, {"name": "Antonis Gaitanidis", "position": "Atacante", "number": "78", "market_value": "350 mil \u20ac", "age": "20", "date_of_birth": "18/03/2000", "nation": "Gr\u00e9cia", "contract_expires": "30/06/2022"}, {"name": "Karol Swiderski", "position": "Centroavante", "number": "9", "market_value": "4,00 milh\u00f5es \u20ac", "age": "23", "date_of_birth": "23/01/1997", "nation": "Pol\u00f3nia", "contract_expires": "30/06/2022"}, {"name": "Antonio Colak", "position": "Centroavante", "number": "25", "market_value": "4,00 milh\u00f5es \u20ac", "age": "27", "date_of_birth": "17/09/1993", "nation": "Cro\u00e1cia", "contract_expires": "30/06/2024"}, {"name": "Georgios Koutsias", "position": "Centroavante", "number": "70", "market_value": "-\u00a0\u20ac", "age": "16", "date_of_birth": "08/02/2004", "nation": "Gr\u00e9cia", "contract_expires": "30/06/2023"}]}]}